2.sequential/spsram/sram/spsram.v
module spsram
#(
	parameter	BW_DATA	= 32,
	parameter	BW_ADDR	= 5
)
(
	output		[BW_DATA-1:0]	o_data,
	input		[BW_DATA-1:0]	i_data,
	input		[BW_ADDR-1:0]	i_addr,
	input		            	i_wen,
	input		            	i_cen,
	input		            	i_oen,
	input		            	i_clk
);

// mem wr
	reg			[BW_DATA-1:0]	mem[0:2**BW_ADDR-1];
	always @(posedge i_clk) begin
		if(i_cen && i_wen) begin
			mem[i_addr] <= i_data;
		end else begin
			mem[i_addr] <= mem[i_addr];
		end
	end

// mem rd
	`ifdef	SPSRAM_ASYNC
		assign o_data 	=	!i_oen			?	'bz			:
							i_cen && !i_wen ?	mem[i_addr]	:	'bx;

	`else
		reg		[BW_DATA-1:0]	o_data;
		always @(posedge i_clk) begin
			if(i_oen) begin
				if(i_cen && !i_wen) begin
					o_data	<=	mem[i_addr];
				end else begin
					o_data	<=	'bx;
				end
			end else begin
				o_data	<=	'bz;
			end
		end
	`endif

endmodule

2.sequential/spsram/sram/spsram_tb.v
`define CLKFREQ		100
`define SIMCYCLE	32
`define BW_DATA		32
`define BW_ADDR		4

`define SPSRAM_ASYNC

`include "spsram.v"

module spsram_tb;

// ========================================
// DUT Signals & Instantiation
// ========================================
	wire	[`BW_DATA-1:0]	o_data;
	reg		[`BW_DATA-1:0]	i_data;
	reg		[`BW_ADDR-1:0]	i_addr;
	reg						i_wen;
	reg						i_cen;
	reg						i_oen;
	reg						i_clk;
	
spsram
#(
	.BW_DATA		(`BW_DATA),
	.BW_ADDR		(`BW_ADDR)
)
u_spsram(
	.o_data			(o_data		),
	.i_data			(i_data		),           
	.i_addr			(i_addr		),           
	.i_wen			(i_wen		),           
	.i_cen			(i_cen		),           
	.i_oen          (i_oen		), 
	.i_clk			(i_clk		)
);

// ========================================
// Clock
// ========================================

always	#(500/`CLKFREQ)		i_clk = ~i_clk;

// ========================================
// Task
// ========================================
reg		[4*32-1:0]	taskState;

task init;
	begin
		i_data	=	0;
		i_addr	=	0;
		i_wen	=	0; 
		i_cen	=	0; 
		i_oen	=	0; 
		i_clk	=	0;
	end
endtask

task memWR;
	input	[`BW_ADDR-1:0]	ti_addr;
	input	[`BW_DATA-1:0]	ti_data;
	begin
		@(negedge i_clk) begin
			taskState	= "WR";
			i_data		= ti_data;
			i_addr		= ti_addr;
			i_wen		= 1;
			i_cen		= 1;
			i_oen		= 0;
		end
	end
endtask

task memRD;
	input	[`BW_ADDR-1:0]	ti_addr;
	begin
		@(negedge i_clk) begin
			taskState		= "RD";
			i_addr			= ti_addr;
			i_wen			= 0;
			i_cen			= 1;
			i_oen			= 1;
		end
	end
endtask

// ========================================
// Test Stimulus
// ========================================
integer	i, j;
initial begin
	init();
	#(4*1000/`CLKFREQ);
	
	for (i=0; i<`SIMCYCLE; i++) begin
		memWR(i,i);
	end
	for (i=0; i<`SIMCYCLE; i++) begin
		memRD(i);
	end
	$finish;
end

// ========================================
// Dump VCD
// ========================================
reg [8*32-1:0] vcd_file;
initial begin
	if($value$plusargs("vcd_file=%s", vcd_file)) begin
		$dumpfile(vcd_file);
		$dumpvars;
	end else begin
		$dumpfile("spsram.vcd");
		$dumpvars;
	end
end
endmodule

//DUMP VCD

2.sequential/spsram/sram/spsram.vcd
$date
	Thu Jun 27 19:56:47 2024
$end
$version
	Icarus Verilog
$end
$timescale
	1s
$end
$scope module spsram_tb $end
$var wire 32 ! o_data [31:0] $end
$var reg 5 " i_addr [4:0] $end
$var reg 1 # i_cen $end
$var reg 1 $ i_clk $end
$var reg 32 % i_data [31:0] $end
$var reg 1 & i_oen $end
$var reg 1 ' i_wen $end
$var reg 128 ( taskState [127:0] $end
$var reg 256 ) vcd_file [255:0] $end
$var integer 32 * i [31:0] $end
$scope module u_spsram $end
$var wire 5 + i_addr [4:0] $end
$var wire 1 # i_cen $end
$var wire 1 $ i_clk $end
$var wire 32 , i_data [31:0] $end
$var wire 1 & i_oen $end
$var wire 1 ' i_wen $end
$var wire 32 - o_data [31:0] $end
$upscope $end
$scope task init $end
$upscope $end
$scope task memRD $end
$var reg 5 . ti_addr [4:0] $end
$upscope $end
$scope task memWR $end
$var reg 5 / ti_addr [4:0] $end
$var reg 32 0 ti_data [31:0] $end
$upscope $end
$upscope $end
$enddefinitions $end
#0
$dumpvars
bx 0
bx /
bx .
bz -
b0 ,
b0 +
bx *
b1110011011100000111001101110010011000010110110100101110011101100110001101100100 )
bx (
0'
0&
b0 %
0$
0#
b0 "
bz !
$end
#5
1$
#10
0$
#15
1$
#20
0$
#25
1$
#30
0$
#35
1$
#40
1#
1'
b101011101010010 (
0$
b1 0
b1 /
b1 *
#45
1$
#50
b10 0
b10 /
b10 *
b1 "
b1 +
b1 %
b1 ,
0$
#55
1$
#60
b11 0
b11 /
b11 *
b10 "
b10 +
b10 %
b10 ,
0$
#65
1$
#70
b100 0
b100 /
b100 *
b11 "
b11 +
b11 %
b11 ,
0$
#75
1$
#80
b101 0
b101 /
b101 *
b100 "
b100 +
b100 %
b100 ,
0$
#85
1$
#90
b110 0
b110 /
b110 *
b101 "
b101 +
b101 %
b101 ,
0$
#95
1$
#100
b111 0
b111 /
b111 *
b110 "
b110 +
b110 %
b110 ,
0$
#105
1$
#110
b1000 0
b1000 /
b1000 *
b111 "
b111 +
b111 %
b111 ,
0$
#115
1$
#120
b1001 0
b1001 /
b1001 *
b1000 "
b1000 +
b1000 %
b1000 ,
0$
#125
1$
#130
b1010 0
b1010 /
b1010 *
b1001 "
b1001 +
b1001 %
b1001 ,
0$
#135
1$
#140
b1011 0
b1011 /
b1011 *
b1010 "
b1010 +
b1010 %
b1010 ,
0$
#145
1$
#150
b1100 0
b1100 /
b1100 *
b1011 "
b1011 +
b1011 %
b1011 ,
0$
#155
1$
#160
b1101 0
b1101 /
b1101 *
b1100 "
b1100 +
b1100 %
b1100 ,
0$
#165
1$
#170
b1110 0
b1110 /
b1110 *
b1101 "
b1101 +
b1101 %
b1101 ,
0$
#175
1$
#180
b1111 0
b1111 /
b1111 *
b1110 "
b1110 +
b1110 %
b1110 ,
0$
#185
1$
#190
b10000 0
b10000 /
b10000 *
b1111 "
b1111 +
b1111 %
b1111 ,
0$
#195
1$
#200
b10001 0
b10001 /
b10001 *
b10000 "
b10000 +
b10000 %
b10000 ,
0$
#205
1$
#210
b10010 0
b10010 /
b10010 *
b10001 "
b10001 +
b10001 %
b10001 ,
0$
#215
1$
#220
b10011 0
b10011 /
b10011 *
b10010 "
b10010 +
b10010 %
b10010 ,
0$
#225
1$
#230
b10100 0
b10100 /
b10100 *
b10011 "
b10011 +
b10011 %
b10011 ,
0$
#235
1$
#240
b10101 0
b10101 /
b10101 *
b10100 "
b10100 +
b10100 %
b10100 ,
0$
#245
1$
#250
b10110 0
b10110 /
b10110 *
b10101 "
b10101 +
b10101 %
b10101 ,
0$
#255
1$
#260
b10111 0
b10111 /
b10111 *
b10110 "
b10110 +
b10110 %
b10110 ,
0$
#265
1$
#270
b11000 0
b11000 /
b11000 *
b10111 "
b10111 +
b10111 %
b10111 ,
0$
#275
1$
#280
b11001 0
b11001 /
b11001 *
b11000 "
b11000 +
b11000 %
b11000 ,
0$
#285
1$
#290
b11010 0
b11010 /
b11010 *
b11001 "
b11001 +
b11001 %
b11001 ,
0$
#295
1$
#300
b11011 0
b11011 /
b11011 *
b11010 "
b11010 +
b11010 %
b11010 ,
0$
#305
1$
#310
b11100 0
b11100 /
b11100 *
b11011 "
b11011 +
b11011 %
b11011 ,
0$
#315
1$
#320
b11101 0
b11101 /
b11101 *
b11100 "
b11100 +
b11100 %
b11100 ,
0$
#325
1$
#330
b11110 0
b11110 /
b11110 *
b11101 "
b11101 +
b11101 %
b11101 ,
0$
#335
1$
#340
b11111 0
b11111 /
b11111 *
b11110 "
b11110 +
b11110 %
b11110 ,
0$
#345
1$
#350
b0 .
b0 *
b11111 "
b11111 +
b11111 %
b11111 ,
0$
#355
1$
#360
b0 !
b0 -
b1 .
b1 *
1&
0'
b0 "
b0 +
b101001001000100 (
0$
#365
1$
#370
b1 !
b1 -
b10 .
b10 *
b1 "
b1 +
0$
#375
1$
#380
b10 !
b10 -
b11 .
b11 *
b10 "
b10 +
0$
#385
1$
#390
b11 !
b11 -
b100 .
b100 *
b11 "
b11 +
0$
#395
1$
#400
b100 !
b100 -
b101 .
b101 *
b100 "
b100 +
0$
#405
1$
#410
b101 !
b101 -
b110 .
b110 *
b101 "
b101 +
0$
#415
1$
#420
b110 !
b110 -
b111 .
b111 *
b110 "
b110 +
0$
#425
1$
#430
b111 !
b111 -
b1000 .
b1000 *
b111 "
b111 +
0$
#435
1$
#440
b1000 !
b1000 -
b1001 .
b1001 *
b1000 "
b1000 +
0$
#445
1$
#450
b1001 !
b1001 -
b1010 .
b1010 *
b1001 "
b1001 +
0$
#455
1$
#460
b1010 !
b1010 -
b1011 .
b1011 *
b1010 "
b1010 +
0$
#465
1$
#470
b1011 !
b1011 -
b1100 .
b1100 *
b1011 "
b1011 +
0$
#475
1$
#480
b1100 !
b1100 -
b1101 .
b1101 *
b1100 "
b1100 +
0$
#485
1$
#490
b1101 !
b1101 -
b1110 .
b1110 *
b1101 "
b1101 +
0$
#495
1$
#500
b1110 !
b1110 -
b1111 .
b1111 *
b1110 "
b1110 +
0$
#505
1$
#510
b1111 !
b1111 -
b10000 .
b10000 *
b1111 "
b1111 +
0$
#515
1$
#520
b10000 !
b10000 -
b10001 .
b10001 *
b10000 "
b10000 +
0$
#525
1$
#530
b10001 !
b10001 -
b10010 .
b10010 *
b10001 "
b10001 +
0$
#535
1$
#540
b10010 !
b10010 -
b10011 .
b10011 *
b10010 "
b10010 +
0$
#545
1$
#550
b10011 !
b10011 -
b10100 .
b10100 *
b10011 "
b10011 +
0$
#555
1$
#560
b10100 !
b10100 -
b10101 .
b10101 *
b10100 "
b10100 +
0$
#565
1$
#570
b10101 !
b10101 -
b10110 .
b10110 *
b10101 "
b10101 +
0$
#575
1$
#580
b10110 !
b10110 -
b10111 .
b10111 *
b10110 "
b10110 +
0$
#585
1$
#590
b10111 !
b10111 -
b11000 .
b11000 *
b10111 "
b10111 +
0$
#595
1$
#600
b11000 !
b11000 -
b11001 .
b11001 *
b11000 "
b11000 +
0$
#605
1$
#610
b11001 !
b11001 -
b11010 .
b11010 *
b11001 "
b11001 +
0$
#615
1$
#620
b11010 !
b11010 -
b11011 .
b11011 *
b11010 "
b11010 +
0$
#625
1$
#630
b11011 !
b11011 -
b11100 .
b11100 *
b11011 "
b11011 +
0$
#635
1$
#640
b11100 !
b11100 -
b11101 .
b11101 *
b11100 "
b11100 +
0$
#645
1$
#650
b11101 !
b11101 -
b11110 .
b11110 *
b11101 "
b11101 +
0$
#655
1$
#660
b11110 !
b11110 -
b11111 .
b11111 *
b11110 "
b11110 +
0$
#665
1$
#670
b11111 !
b11111 -
b100000 *
b11111 "
b11111 +
0$
