project_0/05_fsm_traffic_light/traffic_light_controller.v
module mode_fsm
(
	output reg 		mode,
	input			i_perad,
	input			i_stop,
	input			i_clk,
	input			i_rstn
);


	always @(*) begin
		if (!i_rstn)     	  mode <= #1 1'b0;		// s0	
	end

	always @(posedge i_clk) begin
		if (mode == 0) begin
			if (i_perad == 1) mode <= #1 1'b1;		// s1
			else			  mode <= #1 1'b0;	
		end
		else if (mode == 1) begin
			if (i_stop  == 1) mode <= #1 1'b0;		// s0
			else 	  	      mode <= #1 1'b1;
		end
	end

endmodule
		

module light_fsm
(
	output reg	[8*6-1:0]	o_la,
	output reg	[8*6-1:0]	o_lb,
	input					mode,
	input					i_ta,
	input					i_tb,
	input					i_clk,
	input					i_rstn
);
	reg	   		[1:0]		state;

	always @(*) begin
		if (!i_rstn) begin
						state <= #1 2'b0;		// s0
						o_la  <= #1 "green";
						o_lb  <= #1 "red";
		end
	end

	always @(posedge i_clk) begin
		if (state == 0) begin
			if(i_ta == 1 & mode == 0) begin
						state <= #1 2'b1;		// s1
						o_la  <= #1 "yellow";
						o_lb  <= #1 "red";
			end else begin
						state <= state;
		    end
		end
		else if (state == 1) begin
						state <= #1 2'h2;		// s2
						o_la  <= #1 "red";
						o_lb  <= #1 "green";
		end
		else if (state == 2) begin
			if(i_tb == 1 & mode == 0) begin
						state <= #1 2'h3; 		// s3
						o_la  <= #1 "red";
						o_lb  <= #1 "yellow";
			end else begin
						state <= state;
		    end
	    end
		else if (state == 3) begin
						state <= #1 2'h0;		// s0
						o_la  <= #1 "green";
						o_lb  <= #1 "red";
		end
	end

endmodule

project_0/05_fsm_traffic_light/traffic_light_controller_tb.v
`define CLKFREQ		100
`define SIMCYCLE	50

`include "traffic_light_controller.v"

module traffic_light_controller_tb;

	wire				mode;
	wire [8*6-1:0]		o_la;
	wire [8*6-1:0]		o_lb;
	reg					i_ta;
	reg					i_tb;
	reg					i_stop;
	reg					i_perad;
	reg					i_clk;
	reg					i_rstn;

	mode_fsm
	u_mode_fsm
	(
		.mode		(mode	),
		.i_stop		(i_stop	),
		.i_perad	(i_perad),
		.i_clk		(i_clk	),
		.i_rstn		(i_rstn	)
	);	

	light_fsm
	u_light_fsm
	(
		.o_la		(o_la	),
		.o_lb		(o_lb	),
		.mode		(mode	),
		.i_ta		(i_ta	),
		.i_tb		(i_tb	),
		.i_clk		(i_clk	),
		.i_rstn		(i_rstn	)
	);	

	always	#(1000/`CLKFREQ)		i_clk = ~i_clk;

	task init;
		begin
		i_ta		= 0;
		i_tb		= 0;
		i_stop		= 0;
		i_perad		= 0;
		i_clk		= 0;
		i_rstn		= 0;
		@(posedge i_clk);
		end
	endtask

	integer i;
	initial begin
		init();
		
		for(i=0; i<`SIMCYCLE; i++) begin
		#1;
		i_ta		=  $random;
		i_tb		=  $random;
		i_stop		=  $random;
		i_perad		=  $random;
		repeat(1) @(posedge i_clk);
		end

		repeat(2) @(posedge i_clk);
		$finish;
		
	end

	reg [8*32-1:0] vcd_file;
	initial begin
		if($value$plusargs("vcd_file=%s", vcd_file)) begin
			$dumpfile(vcd_file);
			$dumpvars;
		end else begin
			$dumpfile("traffic_light_controller.vcd");
			$dumpvars;
		end
	end

endmodule

project_0/05_fsm_traffic_light/vcd/traffic_light_controller.vcd
$date
	Sat Jul  6 21:41:44 2024
$end
$version
	Icarus Verilog
$end
$timescale
	1s
$end
$scope module traffic_light_controller_tb $end
$var wire 48 ! o_lb [47:0] $end
$var wire 48 " o_la [47:0] $end
$var wire 1 # mode $end
$var reg 1 $ i_clk $end
$var reg 1 % i_perad $end
$var reg 1 & i_rstn $end
$var reg 1 ' i_stop $end
$var reg 1 ( i_ta $end
$var reg 1 ) i_tb $end
$var reg 256 * vcd_file [255:0] $end
$var integer 32 + i [31:0] $end
$scope module u_light_fsm $end
$var wire 1 $ i_clk $end
$var wire 1 & i_rstn $end
$var wire 1 ( i_ta $end
$var wire 1 ) i_tb $end
$var wire 1 # mode $end
$var reg 48 , o_la [47:0] $end
$var reg 48 - o_lb [47:0] $end
$var reg 2 . state [1:0] $end
$upscope $end
$scope module u_mode_fsm $end
$var wire 1 $ i_clk $end
$var wire 1 % i_perad $end
$var wire 1 & i_rstn $end
$var wire 1 ' i_stop $end
$var reg 1 # mode $end
$upscope $end
$scope task init $end
$upscope $end
$upscope $end
$enddefinitions $end
#0
$dumpvars
bx .
bx -
bx ,
bx +
b111011001100011011001000010111101110100011100100110000101100110011001100110100101100011010111110110110001101001011001110110100001110100010111110110001101101111011011100111010001110010011011110110110001101100011001010111001000101110011101100110001101100100 *
0)
0(
0'
0&
0%
0$
x#
bx "
bx !
$end
#1
b11100100110010101100100 !
b11100100110010101100100 -
b110011101110010011001010110010101101110 "
b110011101110010011001010110010101101110 ,
b0 .
0#
#10
b0 +
1$
#11
1%
1'
1)
#20
0$
#30
b1 +
1$
#31
1#
0%
1(
#40
0$
#50
b10 +
1$
#51
0#
1%
0'
#60
0$
#70
b11 +
1$
#71
b11110010110010101101100011011000110111101110111 "
b11110010110010101101100011011000110111101110111 ,
b1 .
1#
0%
1'
0)
#80
0$
#90
b100 +
1$
#91
0#
b110011101110010011001010110010101101110 !
b110011101110010011001010110010101101110 -
b11100100110010101100100 "
b11100100110010101100100 ,
b10 .
1%
#100
0$
#110
b101 +
1$
#111
1#
0%
0'
1)
0(
#120
0$
#130
b110 +
1$
#131
1%
#140
0$
#150
b111 +
1$
#151
0%
1'
1(
#160
0$
#170
b1000 +
1$
#171
0#
1%
0'
0)
0(
#180
0$
#190
b1001 +
1$
#191
1#
1'
1)
#200
0$
#210
b1010 +
1$
#211
0#
0%
0'
1(
#220
0$
#230
b1011 +
1$
#231
b11110010110010101101100011011000110111101110111 !
b11110010110010101101100011011000110111101110111 -
b11 .
1'
#240
0$
#250
b1100 +
1$
#251
b11100100110010101100100 !
b11100100110010101100100 -
b110011101110010011001010110010101101110 "
b110011101110010011001010110010101101110 ,
b0 .
0'
0)
0(
#260
0$
#270
b1101 +
1$
#271
1%
1(
#280
0$
#290
b1110 +
1$
#291
1#
b11110010110010101101100011011000110111101110111 "
b11110010110010101101100011011000110111101110111 ,
b1 .
0%
#300
0$
#310
b1111 +
1$
#311
b110011101110010011001010110010101101110 !
b110011101110010011001010110010101101110 -
b11100100110010101100100 "
b11100100110010101100100 ,
b10 .
1%
1'
0(
#320
0$
#330
b10000 +
1$
#331
0#
0%
1)
1(
#340
0$
#350
b10001 +
1$
#351
b11110010110010101101100011011000110111101110111 !
b11110010110010101101100011011000110111101110111 -
b11 .
1%
0(
#360
0$
#370
b10010 +
1$
#371
1#
b11100100110010101100100 !
b11100100110010101100100 -
b110011101110010011001010110010101101110 "
b110011101110010011001010110010101101110 ,
b0 .
0)
#380
0$
#390
b10011 +
1$
#391
0#
0%
1)
#400
0$
#410
b10100 +
1$
#411
1(
#420
0$
#430
b10101 +
1$
#431
b11110010110010101101100011011000110111101110111 "
b11110010110010101101100011011000110111101110111 ,
b1 .
0'
#440
0$
#450
b10110 +
1$
#451
b110011101110010011001010110010101101110 !
b110011101110010011001010110010101101110 -
b11100100110010101100100 "
b11100100110010101100100 ,
b10 .
1%
1'
0)
0(
#460
0$
#470
b10111 +
1$
#471
1#
#480
0$
#490
b11000 +
1$
#491
0#
0%
1)
1(
#500
0$
#510
b11001 +
1$
#511
b11110010110010101101100011011000110111101110111 !
b11110010110010101101100011011000110111101110111 -
b11 .
#520
0$
#530
b11010 +
1$
#531
b11100100110010101100100 !
b11100100110010101100100 -
b110011101110010011001010110010101101110 "
b110011101110010011001010110010101101110 ,
b0 .
0'
0)
0(
#540
0$
#550
b11011 +
1$
#551
1%
1'
#560
0$
#570
b11100 +
1$
#571
1#
0%
1)
1(
#580
0$
#590
b11101 +
1$
#591
0#
0'
#600
0$
#610
b11110 +
1$
#611
b11110010110010101101100011011000110111101110111 "
b11110010110010101101100011011000110111101110111 ,
b1 .
1%
#620
0$
#630
b11111 +
1$
#631
b110011101110010011001010110010101101110 !
b110011101110010011001010110010101101110 -
b11100100110010101100100 "
b11100100110010101100100 ,
b10 .
1#
0%
1'
#640
0$
#650
b100000 +
1$
#651
0#
0)
0(
#660
0$
#670
b100001 +
1$
#671
1%
#680
0$
#690
b100010 +
1$
#691
1#
0%
#700
0$
#710
b100011 +
1$
#711
0#
#720
0$
#730
b100100 +
1$
#731
1%
0'
1)
#740
0$
#750
b100101 +
1$
#751
b11110010110010101101100011011000110111101110111 !
b11110010110010101101100011011000110111101110111 -
b11 .
1#
1'
1(
#760
0$
#770
b100110 +
1$
#771
0#
b11100100110010101100100 !
b11100100110010101100100 -
b110011101110010011001010110010101101110 "
b110011101110010011001010110010101101110 ,
b0 .
0'
0)
0(
#780
0$
#790
b100111 +
1$
#791
1#
1'
#800
0$
#810
b101000 +
1$
#811
0#
0'
#820
0$
#830
b101001 +
1$
#831
1#
0%
1(
#840
0$
#850
b101010 +
1$
#851
1)
#860
0$
#870
b101011 +
1$
#871
0(
#880
0$
#890
b101100 +
1$
#891
0)
1(
#900
0$
#910
b101101 +
1$
#911
1%
1'
#920
0$
#930
b101110 +
1$
#931
0#
0%
0'
0(
#940
0$
#950
b101111 +
1$
#951
1(
#960
0$
#970
b110000 +
1$
#971
b11110010110010101101100011011000110111101110111 "
b11110010110010101101100011011000110111101110111 ,
b1 .
1%
1'
1)
0(
#980
0$
#990
b110001 +
1$
#991
b110011101110010011001010110010101101110 !
b110011101110010011001010110010101101110 -
b11100100110010101100100 "
b11100100110010101100100 ,
b10 .
1#
#1000
0$
#1010
b110010 +
1$
#1011
0#
#1020
0$
#1030
1$
#1031
b11110010110010101101100011011000110111101110111 !
b11110010110010101101100011011000110111101110111 -
b11 .
1#
