2.sequential/seq_detect_moore/seq_detect_moore.v
module seq_detect_moore
(
	output reg		o_out,
	input			i_seq,
	input			i_clk,
	input			i_rstn
);

	reg		[2:0]	cstate;
	reg		[2:0]	nstate;
	reg				seq;

	parameter	S_IDLE	=	3'b000;
	parameter	S_H  	=	3'b001;
	parameter	S_HL	=	3'b010;
	parameter	S_HLH	=	3'b011;
	parameter	S_HLHH	=	3'b100;

	always @(posedge i_clk or negedge i_rstn) begin
		if(!i_rstn) begin
			cstate	<= S_IDLE;
			seq		<= 1'b0;
		end else begin
			cstate	<= nstate;
			seq		<= i_seq;
		end
	end

	always @(*) begin
		if(seq == 1'b0) begin
			case(cstate)
				S_IDLE	:	nstate = S_IDLE; 
				S_H     :	nstate = S_HL;   
				S_HL    :	nstate = S_IDLE;  
				S_HLH   :	nstate = S_HL; 
				S_HLHH  :	nstate = S_IDLE;
			endcase
		end else begin
			case(cstate)
				S_IDLE	:	nstate = S_H; 
				S_H     :	nstate = S_H;   
				S_HL    :	nstate = S_HLH;  
				S_HLH   :	nstate = S_HLHH; 
				S_HLHH  :	nstate = S_H;
			endcase
		end
	end

	always @(*) begin
		case(cstate)
			S_HLHH	: 	o_out	= 1'b1;
			default	:	o_out	= 1'b0;
		endcase
	end

endmodule

2.sequential/seq_detect_moore/seq_detect_moore_tb.v
`define CLKFREQ		100
`define SIMCYCLE	50

`include "seq_detect_moore.v"

module seq_detect_moore_tb;

// ========================================
// DUT Signals & Instantiation
// ========================================
	wire	o_out;
	reg		i_seq;
	reg		i_clk;
	reg		i_rstn;

	seq_detect_moore
	u_seq_detect_moore
	(
		.o_out	(o_out),
		.i_seq	(i_seq),
		.i_clk	(i_clk),
		.i_rstn	(i_rstn)
	);

// ========================================
// Clock
// ========================================
always #(500/`CLKFREQ) i_clk = ~i_clk;

// ========================================
// Task
// ========================================
task init;
	begin
		i_seq  = 1'b0;
		i_clk  = 1'b0;
		i_rstn = 1'b0;
	end
endtask
	
// ========================================
// Test Stimulus
// ========================================
integer i, j;
initial begin
		init();
		
	for(i=0; i<`SIMCYCLE; i++) begin
	j	= $urandom_range(0,10);
	#(( (j*0.1)) * 1000 /`CLKFREQ);
	i_seq = $urandom;
	#((1-(j*0.1)) * 1000 /`CLKFREQ);
    end	
   $finish;
end

// ========================================
// Dump VCD
// ========================================
reg [8*32-1:0] vcd_file;
initial begin
	if($value$plusargs("vcd_file=%s", vcd_file)) begin
		$dumpfile(vcd_file);
		$dumpvars;
	end else begin
		$dumpfile("seq_detect_moore_tb.vcd");
		$dumpvars;
	end
end

endmodule

2.sequential/seq_detect_moore/seq_detect_moore.vcd
$date
	Thu Jun 27 19:45:35 2024
$end
$version
	Icarus Verilog
$end
$timescale
	1s
$end
$scope module seq_detect_moore_tb $end
$var wire 1 ! o_out $end
$var reg 1 " i_clk $end
$var reg 1 # i_rstn $end
$var reg 1 $ i_seq $end
$var reg 256 % vcd_file [255:0] $end
$var integer 32 & i [31:0] $end
$var integer 32 ' j [31:0] $end
$scope module u_seq_detect_moore $end
$var wire 1 " i_clk $end
$var wire 1 # i_rstn $end
$var wire 1 $ i_seq $end
$var reg 3 ( cstate [2:0] $end
$var reg 3 ) nstate [2:0] $end
$var reg 1 ! o_out $end
$var reg 1 * seq $end
$upscope $end
$scope task init $end
$upscope $end
$upscope $end
$enddefinitions $end
#0
$dumpvars
0*
b0 )
b0 (
b110 '
b0 &
b111001101100101011100010101111101100100011001010111010001100101011000110111010001011111011011010110111101101111011100100110010100101110011101100110001101100100 %
0$
0#
0"
0!
$end
#5
1"
#6
1$
#10
b0 '
b1 &
0"
#15
1"
#20
0"
b101 '
b10 &
#25
1"
#30
0"
b10 '
b11 &
#32
0$
#35
1"
#40
0"
b101 '
b100 &
#45
1"
1$
#50
0"
b1000 '
b101 &
#55
1"
#60
b1010 '
b110 &
0"
#65
1"
#70
b111 &
0"
0$
#75
1"
#80
b100 '
b1000 &
0"
#85
1"
#90
0"
b1010 '
b1001 &
#95
1"
#100
b0 '
b1010 &
0"
1$
#105
1"
#110
0"
b1010 '
b1011 &
#115
1"
#120
b100 '
b1100 &
0"
0$
#124
1$
#125
1"
#130
0"
b111 '
b1101 &
#135
1"
#140
b0 '
b1110 &
0"
#145
1"
#150
0"
b10 '
b1111 &
#152
0$
#155
1"
#160
0"
b10000 &
#165
1"
#170
0"
b1001 '
b10001 &
#175
1"
#179
1$
#180
b11 '
b10010 &
0"
#185
1"
#190
0"
b0 '
b10011 &
#195
1"
#200
0"
b111 '
b10100 &
#205
1"
#210
0$
b0 '
b10101 &
0"
#215
1"
#220
0"
b110 '
b10110 &
#225
1"
#226
1$
#230
b10111 &
0"
#235
1"
#236
0$
#240
b100 '
b11000 &
0"
#245
1"
#250
0"
b1010 '
b11001 &
#255
1"
#260
b110 '
b11010 &
0"
#265
1"
#270
b1000 '
b11011 &
0"
#275
1"
#278
1$
#280
b1010 '
b11100 &
0"
#285
1"
#290
b1001 '
b11101 &
0"
0$
#295
1"
#300
b100 '
b11110 &
0"
#305
1"
#310
1$
0"
b0 '
b11111 &
#315
1"
#320
0"
b1000 '
b100000 &
#325
1"
#330
b1 '
b100001 &
0"
#331
0$
#335
1"
#340
0"
b10 '
b100010 &
#342
1$
#345
1"
#350
0"
b1010 '
b100011 &
#355
1"
#360
b111 '
b100100 &
0"
#365
1"
#367
0$
#370
b1000 '
b100101 &
0"
#375
1"
#378
1$
#380
b1010 '
b100110 &
0"
#385
1"
#390
b11 '
b100111 &
0"
#393
0$
#395
1"
#400
0"
b1 '
b101000 &
#401
1$
#405
1"
#410
0"
b101001 &
#411
0$
#415
1"
#420
0"
b100 '
b101010 &
#424
1$
#425
1"
#430
0"
b1000 '
b101011 &
#435
1"
#438
0$
#440
b100 '
b101100 &
0"
#445
1"
#450
0"
b10 '
b101101 &
#452
1$
#455
1"
#460
0"
b101 '
b101110 &
#465
1"
0$
#470
0"
b111 '
b101111 &
#475
1"
#477
1$
#480
b110 '
b110000 &
0"
#485
1"
#490
b1000 '
b110001 &
0"
#495
1"
#498
0$
#500
b110010 &
0"
