project_0/03_adder_cla/carry_lookahead_adder.v
module carry_lookahead_adder
#(
	parameter	BIT		= 32
)
(
	output		[BIT-1:0]			o_data_s,
	output							o_carry,
	input		[BIT-1:0]			i_data_a,
	input		[BIT-1:0]			i_data_b,
	input							i_carry
);
	wire		[(BIT/4)-1:0]		m_data_c;

`ifdef	GENER
	genvar	g;
	generate
		for (g=0; g<BIT/4; g=g+1) begin
			if(g==0) 
				cla_block u_cla_block( m_data_c[g], o_data_s[((g+1)*4)-1:g*4], i_data_a[((g+1)*4)-1:g*4], i_data_b[((g+1)*4)-1:g*4], i_carry);	
			else
				cla_block u_cla_block( m_data_c[g], o_data_s[((g+1)*4)-1:g*4], i_data_a[((g+1)*4)-1:g*4], i_data_b[((g+1)*4)-1:g*4], m_data_c[g-1]);	
		end
	endgenerate

	assign o_carry = m_data_c[BIT-1];

`else
	cla_block u_cla_block1( m_data_c[0], o_data_s[3:0],   i_data_a[3:0],   i_data_b[3:0],   i_carry);	
	cla_block u_cla_block2( m_data_c[1], o_data_s[7:4],   i_data_a[7:4],   i_data_b[7:4],   m_data_c[0]);
	cla_block u_cla_block3( m_data_c[2], o_data_s[11:8],  i_data_a[11:8],  i_data_b[11:8],  m_data_c[1]);
	cla_block u_cla_block4( m_data_c[3], o_data_s[15:12], i_data_a[15:12], i_data_b[15:12], m_data_c[2]);
	cla_block u_cla_block5( m_data_c[4], o_data_s[19:16], i_data_a[19:16], i_data_b[19:16], m_data_c[3]);
	cla_block u_cla_block6( m_data_c[5], o_data_s[23:20], i_data_a[23:20], i_data_b[23:20], m_data_c[4]);
	cla_block u_cla_block7( m_data_c[6], o_data_s[27:24], i_data_a[27:24], i_data_b[27:24], m_data_c[5]);
	cla_block u_cla_block8( o_carry,     o_data_s[31:28], i_data_a[31:28], i_data_b[31:28], m_data_c[6]);
`endif

endmodule

module cla_block
(
	output				o_carry,
	output	[3:0]		o_data_s,
	input	[3:0]		i_data_a,
	input	[3:0]		i_data_b,
	input				i_carry
);
	wire	[2:0]		m_data_c;
	wire	[3:0]		g;
	wire	[3:0]		p;

	assign g[0]		= i_data_a[0] & i_data_b[0];
	assign g[1]		= i_data_a[1] & i_data_b[1];
	assign g[2]		= i_data_a[2] & i_data_b[2];
	assign g[3]		= i_data_a[3] & i_data_b[3];

	assign p[0]		= i_data_a[0] | i_data_b[0];
	assign p[1]		= i_data_a[1] | i_data_b[1];
	assign p[2]		= i_data_a[2] | i_data_b[2];
	assign p[3]		= i_data_a[3] | i_data_b[3];

	assign m_data_c[0]		= g[0] | (p[0] & i_carry);
	assign m_data_c[1]		= g[1] | (p[1] & m_data_c[0]);
	assign m_data_c[2]		= g[2] | (p[2] & m_data_c[1]);
	assign o_carry			= g[3] | (p[3] & m_data_c[2]);

	assign o_data_s[0]		= (i_data_a[0] ^ i_data_b[0]) ^ i_carry;
	assign o_data_s[1]		= (i_data_a[1] ^ i_data_b[1]) ^ m_data_c[0];
	assign o_data_s[2]		= (i_data_a[2] ^ i_data_b[2]) ^ m_data_c[1];
	assign o_data_s[3]		= (i_data_a[3] ^ i_data_b[3]) ^ m_data_c[2];


endmodule

module compare_adder
#(
	parameter	BIT		= 32
)
(
	output	[BIT-1:0]		o_data_s,
	output					o_carry,
	input	[BIT-1:0]		i_data_a,
	input	[BIT-1:0]		i_data_b,
	input					i_carry
);

	assign {o_carry, o_data_s} = i_data_a + i_data_b + i_carry;

endmodule

project_0/03_adder_cla/carry_lookahead_adder_tb.v
`define CLKFREQ		100
`define SIMCYCLE	10
`define BIT			32
`define VEC			10

`include "carry_lookahead_adder.v"

`define GENER
module carry_lookahead_adder_tb;

	wire	[`BIT-1:0]	o_data_s;
	wire				o_carry;
	reg		[`BIT-1:0]	i_data_a;
	reg		[`BIT-1:0]	i_data_b;
	reg					i_carry;
	reg					i_clk;

	carry_lookahead_adder
	#(
		.BIT		(`BIT)
	)
	u_carry_lookahead_adder
	(
		.o_data_s	(o_data_s	),
		.o_carry	(o_carry	),
		.i_data_a	(i_data_a	),
		.i_data_b	(i_data_b	),
		.i_carry	(i_carry	)
	);

	wire	[31:0]	o_data_s_comp;
	wire			o_carry_comp;

	compare_adder
	#(
		.BIT		(`BIT)
	)
	u_compare_adder
	(
		.o_data_s	(o_data_s_comp	),
		.o_carry	(o_carry_comp	),
		.i_data_a	(i_data_a     	),
		.i_data_b	(i_data_b     	),
		.i_carry	(i_carry     	)
	);

	reg		[`BIT:0]	test_vec	[0:`VEC-1];
	reg		[`BIT:0]	vo_data_s	[0:`VEC-1];
	reg		  	 		vo_carry	[0:`VEC-1];
	reg		[`BIT:0]	vi_data_a	[0:`VEC-1];
	reg		[`BIT:0]	vi_data_b	[0:`VEC-1];
	reg					vi_carry	[0:`VEC-1];

	initial begin
		$readmemb("./test_vec.py",				test_vec);
		$readmemb("./vec_test/o_data.vec",		vo_data_s);
		$readmemb("./vec_test/o_carry.vec",		vo_carry);
		$readmemb("./vec_test/i_data_a.vec",	vi_data_a);
		$readmemb("./vec_test/i_data_b.vec",	vi_data_b);
		$readmemb("./vec_test/i_carry.vec",		vi_carry);
	end
	always	#(500/`CLKFREQ)		i_clk = ~i_clk;

	task init;
		begin
			i_data_a	=	0;
			i_data_b	=	0;
			i_carry		=	0;
			i_clk		=	0;
			@(posedge i_clk);
		end
	endtask

	task vectest;
		input	[$clog2(`VEC)-1:0]	i;
		begin
			i_data_a		= vi_data_a[i];
			i_data_b		= vi_data_b[i];
			i_carry			= vi_carry[i];
			@(posedge i_clk);
            if ({o_carry, o_data_s} !== {o_carry_comp, o_data_s_comp}) begin
                $display("Test failed %d: CLA = %h, CMP = %h", i, {o_carry, o_data_s}, {o_carry_comp, o_data_s_comp});
            end else begin
                $display("Test passed %d", i);
            end
		end
	endtask

	integer	i;
	initial begin
		init();
		
		for (i=0; i<`SIMCYCLE; i++) begin
			vectest(i);
			@(posedge i_clk);
		end

		repeat(2) @(posedge i_clk);
		$finish;
	end

	reg [8*32-1:0] vcd_file;
	initial begin
		if($value$plusargs("vcd_file=%s", vcd_file)) begin
			$dumpfile(vcd_file);
			$dumpvars;
		end else begin
			$dumpfile("carry_lookahead_adder.vcd");
			$dumpvars;
		end
	end


endmodule

project_0/03_adder_cla/vcd/carry_lookahead_adder.vcd
$date
	Mon Jul  8 11:23:32 2024
$end
$version
	Icarus Verilog
$end
$timescale
	1s
$end
$scope module carry_lookahead_adder_tb $end
$var wire 32 ! o_data_s_comp [31:0] $end
$var wire 32 " o_data_s [31:0] $end
$var wire 1 # o_carry_comp $end
$var wire 1 $ o_carry $end
$var reg 1 % i_carry $end
$var reg 1 & i_clk $end
$var reg 32 ' i_data_a [31:0] $end
$var reg 32 ( i_data_b [31:0] $end
$var reg 256 ) vcd_file [255:0] $end
$var integer 32 * i [31:0] $end
$scope module u_carry_lookahead_adder $end
$var wire 1 % i_carry $end
$var wire 32 + i_data_a [31:0] $end
$var wire 32 , i_data_b [31:0] $end
$var wire 32 - o_data_s [31:0] $end
$var wire 1 $ o_carry $end
$var wire 8 . m_data_c [7:0] $end
$scope module u_cla_block1 $end
$var wire 1 % i_carry $end
$var wire 4 / i_data_a [3:0] $end
$var wire 4 0 i_data_b [3:0] $end
$var wire 1 1 o_carry $end
$var wire 4 2 p [3:0] $end
$var wire 4 3 o_data_s [3:0] $end
$var wire 3 4 m_data_c [2:0] $end
$var wire 4 5 g [3:0] $end
$upscope $end
$scope module u_cla_block2 $end
$var wire 1 6 i_carry $end
$var wire 4 7 i_data_a [3:0] $end
$var wire 4 8 i_data_b [3:0] $end
$var wire 1 9 o_carry $end
$var wire 4 : p [3:0] $end
$var wire 4 ; o_data_s [3:0] $end
$var wire 3 < m_data_c [2:0] $end
$var wire 4 = g [3:0] $end
$upscope $end
$scope module u_cla_block3 $end
$var wire 1 > i_carry $end
$var wire 4 ? i_data_a [3:0] $end
$var wire 4 @ i_data_b [3:0] $end
$var wire 1 A o_carry $end
$var wire 4 B p [3:0] $end
$var wire 4 C o_data_s [3:0] $end
$var wire 3 D m_data_c [2:0] $end
$var wire 4 E g [3:0] $end
$upscope $end
$scope module u_cla_block4 $end
$var wire 1 F i_carry $end
$var wire 4 G i_data_a [3:0] $end
$var wire 4 H i_data_b [3:0] $end
$var wire 1 I o_carry $end
$var wire 4 J p [3:0] $end
$var wire 4 K o_data_s [3:0] $end
$var wire 3 L m_data_c [2:0] $end
$var wire 4 M g [3:0] $end
$upscope $end
$scope module u_cla_block5 $end
$var wire 1 N i_carry $end
$var wire 4 O i_data_a [3:0] $end
$var wire 4 P i_data_b [3:0] $end
$var wire 1 Q o_carry $end
$var wire 4 R p [3:0] $end
$var wire 4 S o_data_s [3:0] $end
$var wire 3 T m_data_c [2:0] $end
$var wire 4 U g [3:0] $end
$upscope $end
$scope module u_cla_block6 $end
$var wire 1 V i_carry $end
$var wire 4 W i_data_a [3:0] $end
$var wire 4 X i_data_b [3:0] $end
$var wire 1 Y o_carry $end
$var wire 4 Z p [3:0] $end
$var wire 4 [ o_data_s [3:0] $end
$var wire 3 \ m_data_c [2:0] $end
$var wire 4 ] g [3:0] $end
$upscope $end
$scope module u_cla_block7 $end
$var wire 1 ^ i_carry $end
$var wire 4 _ i_data_a [3:0] $end
$var wire 4 ` i_data_b [3:0] $end
$var wire 1 a o_carry $end
$var wire 4 b p [3:0] $end
$var wire 4 c o_data_s [3:0] $end
$var wire 3 d m_data_c [2:0] $end
$var wire 4 e g [3:0] $end
$upscope $end
$scope module u_cla_block8 $end
$var wire 1 f i_carry $end
$var wire 4 g i_data_a [3:0] $end
$var wire 4 h i_data_b [3:0] $end
$var wire 1 $ o_carry $end
$var wire 4 i p [3:0] $end
$var wire 4 j o_data_s [3:0] $end
$var wire 3 k m_data_c [2:0] $end
$var wire 4 l g [3:0] $end
$upscope $end
$upscope $end
$scope module u_compare_adder $end
$var wire 1 % i_carry $end
$var wire 32 m i_data_a [31:0] $end
$var wire 32 n i_data_b [31:0] $end
$var wire 32 o o_data_s [31:0] $end
$var wire 1 # o_carry $end
$upscope $end
$scope task init $end
$upscope $end
$scope task vectest $end
$var reg 4 p i [3:0] $end
$upscope $end
$upscope $end
$enddefinitions $end
#0
$dumpvars
bx p
b0 o
b0 n
b0 m
b0 l
b0 k
b0 j
b0 i
b0 h
b0 g
0f
b0 e
b0 d
b0 c
b0 b
0a
b0 `
b0 _
0^
b0 ]
b0 \
b0 [
b0 Z
0Y
b0 X
b0 W
0V
b0 U
b0 T
b0 S
b0 R
0Q
b0 P
b0 O
0N
b0 M
b0 L
b0 K
b0 J
0I
b0 H
b0 G
0F
b0 E
b0 D
b0 C
b0 B
0A
b0 @
b0 ?
0>
b0 =
b0 <
b0 ;
b0 :
09
b0 8
b0 7
06
b0 5
b0 4
b0 3
b0 2
01
b0 0
b0 /
bz0000000 .
b0 -
b0 ,
b0 +
bx *
b101110001011110111011001100011011001000010111101100011011000010111001001110010011110010101111101101100011011110110111101101011011000010110100001100101011000010110010001011111011000010110010001100100011001010111001000101110011101100110001101100100 )
b0 (
b0 '
0&
0%
0$
0#
b0 "
b0 !
$end
#5
1>
19
1^
1f
b111 T
1Y
1a
16
1F
1N
1V
11
b111 <
1A
b100 L
1I
bz1111111 .
1Q
b111 \
b111 d
b10 k
b1011 K
b1101 j
b110 3
b1 ;
b101 C
b1000 S
b101 [
b11010100010110001011010100010110 "
b11010100010110001011010100010110 -
b100 c
b1000 5
b1110 2
b1 =
b1111 :
b1000 E
b1100 B
b1100 M
b1110 J
b1000 U
b1111 R
b101 ]
b1111 Z
b100 e
b1111 b
b10 l
b1010 i
b1010 0
b111 8
b1000 @
b1110 H
b1001 P
b1101 X
b1100 `
b1010 h
b1100 /
b1001 7
b1100 ?
b1100 G
b1110 O
b111 W
b111 _
b10 g
b11010100010110001011010100010110 !
b11010100010110001011010100010110 o
b10101100110110011110100001111010 (
b10101100110110011110100001111010 ,
b10101100110110011110100001111010 n
b100111011111101100110010011100 '
b100111011111101100110010011100 +
b100111011111101100110010011100 m
b0 p
b0 *
1&
#10
0&
#15
1&
#20
0&
#25
0>
09
1$
0N
0I
b10 [
06
b0 <
b0 D
0F
0V
01
b111 k
b11 4
0A
b0 L
bz1100000 .
0Q
b100 \
b11 d
b1011 K
b1011 ;
b1111 C
b1000 S
b110 c
b0 j
b1011 :
b0 l
b10 5
b1011 2
b0 =
b0 E
b1111 B
b0 M
b1011 J
b1 U
b111 R
b100 ]
b1110 Z
b1010 e
b1011 b
b1111 i
b110001010001011111110111110 "
b110001010001011111110111110 -
b1110 3
b11 0
b1011 8
b1001 @
b11 H
b111 P
b110 X
b1011 `
b100 h
b1010 /
b0 7
b110 ?
b1000 G
b1 O
b1100 W
b1010 _
b1011 g
b110001010001011111110111110 !
b110001010001011111110111110 o
1#
1%
b1001011011001110011100110110011 (
b1001011011001110011100110110011 ,
b1001011011001110011100110110011 n
b10111010110000011000011000001010 '
b10111010110000011000011000001010 +
b10111010110000011000011000001010 m
b1 p
b1 *
1&
#30
0&
#35
1&
#40
0&
#45
0$
b11 D
b110 S
0^
16
1f
1>
1V
0Y
b1 k
11
1a
b111 <
19
b10 L
b0 T
bz1010011 .
1Q
b1 \
b100 d
b11 c
b1001 ;
b1100 C
b1101 K
b10 [
b1011 j
b1111 :
b1 l
b1000 5
b1001 2
b1001 =
b1011 B
b10 M
b1000 U
b1110 R
b0 ]
b1 Z
b100 e
b1111 b
b1001 i
b0 4
b10110011001001101101110010010001 "
b10110011001001101101110010010001 -
b1 3
b1001 0
b1111 8
b1000 @
b10 H
b1010 P
b0 X
b101 `
b1001 h
b1000 /
b1001 7
b11 ?
b1011 G
b1100 O
b1 W
b1110 _
b1 g
b10110011001001101101110010010001 !
b10110011001001101101110010010001 o
0#
0%
b10010101000010100010100011111001 (
b10010101000010100010100011111001 ,
b10010101000010100010100011111001 n
b11110000111001011001110011000 '
b11110000111001011001110011000 +
b11110000111001011001110011000 m
b10 p
b10 *
1&
#50
0&
#55
1&
#60
0&
#65
0F
0A
1N
0f
1I
0a
b1 <
06
0>
b0 D
0V
b0 \
b11 k
01
09
b101 L
b111 T
bz0001000 .
0Q
b11 d
1$
b110 ;
b10 K
b1101 S
b1111 3
b1101 C
b100 [
b1100 c
b1001100010011010010110101101111 "
b1001100010011010010110101101111 -
b100 j
b0 5
b1111 2
b1 =
b101 :
b1101 B
b101 M
b1101 J
b101 U
b111 R
b100 Z
b1 e
b1011 b
b1001 l
b1011 i
b1 8
b101 H
b101 P
b100 X
b11 `
b110 /
b101 7
b101 ?
b1101 G
b111 O
b0 W
b1001 _
b1011 g
b1001100010011010010110101101111 !
b1001100010011010010110101101111 o
1#
b10010011010001010101100000011001 (
b10010011010001010101100000011001 ,
b10010011010001010101100000011001 n
b10111001000001111101010101010110 '
b10111001000001111101010101010110 +
b10111001000001111101010101010110 m
b11 p
b11 *
1&
#70
0&
#75
1&
#80
0&
#85
0N
0V
1F
0I
0Q
1^
b101 L
b0 <
1A
b0 T
b111 \
bz0100100 .
1Y
b0 d
b110 k
b1000 j
b1010 ;
b11 C
b1010 K
b1001 S
b1110 [
b101 c
b10 5
b111 2
b100 M
b0 =
b1010 :
b1000 E
b1011 B
b101 J
b0 U
b1001 R
b1111 ]
b1111 Z
b0 e
b100 b
b1010 l
b1110 i
b111 4
b10000101111010011010001110101010 "
b10000101111010011010001110101010 -
b1010 3
b110 0
b10 8
b1001 @
b100 H
b0 P
b1111 X
b0 `
b1110 h
b11 /
b1000 7
b1010 ?
b101 G
b1001 O
b1111 W
b100 _
b1010 g
b10000101111010011010001110101010 !
b10000101111010011010001110101010 o
1%
b11100000111100000100100100100110 (
b11100000111100000100100100100110 ,
b11100000111100000100100100100110 n
b10100100111110010101101010000011 '
b10100100111110010101101010000011 +
b10100100111110010101101010000011 m
b100 p
b100 *
1&
#90
0&
#95
1&
#100
0&
#105
1V
1Q
16
1N
b111 d
11
b11 <
b111 L
bz0111101 .
1I
b100 T
b111 \
b101 k
b101 ;
b1000 K
b11 S
b100 [
b1000 c
b10 j
b1000 5
b1000 2
b1 =
b11 :
b1000 M
b1111 J
b100 U
b1110 R
b100 ]
b111 b
b101 l
b1101 i
b0 4
b101000010000111000001101010000 "
b101000010000111000001101010000 -
b0 3
b1000 0
b1 8
b1100 H
b110 P
b111 X
b110 `
b101 h
b1000 /
b11 7
b1011 G
b1100 O
b1100 W
b1 _
b1101 g
b101000010000111000001101010000 !
b101000010000111000001101010000 o
0%
b1010110011101101100100100011000 (
b1010110011101101100100100011000 ,
b1010110011101101100100100011000 n
b11010001110011001011101000111000 '
b11010001110011001011101000111000 +
b11010001110011001011101000111000 m
b101 p
b101 *
1&
#110
0&
#115
1&
#120
0&
#125
1>
19
0V
0Q
0f
b111 <
b0 \
0a
06
0N
b101 L
b0 d
b0 T
b110 4
01
b111 D
bz0100110 .
0I
b100 k
b1100 S
b110 [
b1001 3
b0 ;
b1011 C
b1010 K
b1111 c
b11111011011001010101100001001 "
b11111011011001010101100001001 -
b1 j
b0 U
b1100 R
b1000 ]
b1110 Z
b10 5
b111 2
b1111 :
b1011 E
b1111 B
b100 M
b101 J
b1110 b
b100 l
b10 0
b101 8
b1011 @
b101 H
b0 P
b1000 X
b1000 `
b111 /
b1011 7
b1111 ?
b100 G
b1110 W
b110 _
b1100 g
b11111011011001010101100001001 !
b11111011011001010101100001001 o
b1011000100000000101101101010010 (
b1011000100000000101101101010010 ,
b1011000100000000101101101010010 n
b11000110111011000100111110110111 '
b11000110111011000100111110110111 +
b11000110111011000100111110110111 m
b110 p
b110 *
1&
#130
0&
#135
1&
#140
0&
#145
b0 D
06
0>
0N
01
b1 <
09
0F
0I
0^
0$
b0 L
b110 \
b0 k
0A
b1 T
bz0000000 .
0Y
b10 ;
b111 C
b1111 K
b1010 S
b1101 [
b1010 c
b111 j
b0 M
b0 l
b1 5
b1101 2
b1 :
b0 E
b111 B
b1111 J
b1 U
b1001 R
b110 ]
b111 Z
b1010 b
b111 i
b1 4
b1111010110110101111011100101111 "
b1111010110110101111011100101111 -
b1111 3
b101 0
b1 8
b1 @
b11 H
b1001 P
b110 X
b10 `
b0 h
b1001 /
b1 7
b110 ?
b1100 G
b1 O
b111 W
b1000 _
b111 g
b1111010110110101111011100101111 !
b1111010110110101111011100101111 o
0#
1%
b10011010010011000100010101 (
b10011010010011000100010101 ,
b10011010010011000100010101 n
b1111000011100011100011000011001 '
b1111000011100011100011000011001 +
b1111000011100011100011000011001 m
b111 p
b111 *
1&
#150
0&
#155
1&
#160
0&
#165
1f
1a
06
01
1V
b1 D
1Q
b10 S
1>
b0 4
b0 <
b111 k
bz1010010 .
19
b101 T
b1 \
b111 d
1$
b1100 K
b11 [
b0 c
b1001 j
b111 ;
b1110 C
b0 5
b1100 J
b1111 2
b1000 =
b1111 :
b1101 B
b101 U
b1101 R
b1 ]
b1 Z
b1 e
b1111 b
b1001 l
b1111 i
b10010000001100101100111001111111 "
b10010000001100101100111001111111 -
b1111 3
b1100 0
b1000 8
b1100 @
b1000 H
b101 P
b1 X
b101 `
b1001 h
1#
b11 /
b1111 7
b1 ?
b100 G
b1101 O
b1 W
b1011 _
b1111 g
b10010000001100101100111001111111 !
b10010000001100101100111001111111 o
0%
b10010101000101011000110010001100 (
b10010101000101011000110010001100 ,
b10010101000101011000110010001100 n
b11111011000111010100000111110011 '
b11111011000111010100000111110011 +
b11111011000111010100000111110011 m
b1000 p
b1000 *
1&
#170
0&
#175
1&
#180
0&
#185
0$
b0 k
1F
1A
0f
1N
0a
1I
b1 C
0>
16
09
b111 L
b0 d
bz0011101 .
11
b110 D
b101 T
b111 \
b1101 ;
b100 K
b10 S
b1110 [
b1001 c
b1111 j
b0 =
b100 M
b0 e
b1000 5
b1110 2
b1100 :
b10 E
b1111 B
b1111 J
b100 U
b110 ]
b111 Z
b1001 b
b0 l
b0 4
b11111001111000100100000111010111 "
b11111001111000100100000111010111 -
b111 3
b1110 0
b100 8
b1011 @
b1110 H
b111 X
b1000 `
b1101 h
b1000 /
b1000 7
b110 ?
b101 G
b1100 O
b110 W
b1 _
b10 g
b11111001111000100100000111010111 !
b11111001111000100100000111010111 o
0#
1%
b11011000011101011110101101001110 (
b11011000011101011110101101001110 ,
b11011000011101011110101101001110 n
b100001011011000101011010001000 '
b100001011011000101011010001000 +
b100001011011000101011010001000 m
b1001 p
b1001 *
1&
#190
0&
#195
1&
#200
0&
#205
b1010 *
1&
