project_0/03_adder_cla/carry_lookahead_adder.v
module carry_lookahead_adder
#(
	parameter	BIT		= 32
)
(
	output		[BIT-1:0]			o_data_s,
	output							o_carry,
	input		[BIT-1:0]			i_data_a,
	input		[BIT-1:0]			i_data_b,
	input							i_carry
);
	wire		[(BIT/4)-1:0]		m_data_c;

`ifdef	GENER
	genvar	g;
	generate
		for (g=0; g<BIT/4; g=g+1) begin
			if(g==0) 
				cla_block u_cla_block( m_data_c[g], o_data_s[((g+1)*4)-1:g*4], i_data_a[((g+1)*4)-1:g*4], i_data_b[((g+1)*4)-1:g*4], i_carry);	
			else
				cla_block u_cla_block( m_data_c[g], o_data_s[((g+1)*4)-1:g*4], i_data_a[((g+1)*4)-1:g*4], i_data_b[((g+1)*4)-1:g*4], m_data_c[g-1]);	
		end
	endgenerate

	assign o_carry = m_data_c[BIT-1];

`else
	cla_block u_cla_block1( m_data_c[0], o_data_s[3:0],   i_data_a[3:0],   i_data_b[3:0],   i_carry);	
	cla_block u_cla_block2( m_data_c[1], o_data_s[7:4],   i_data_a[7:4],   i_data_b[7:4],   m_data_c[0]);
	cla_block u_cla_block3( m_data_c[2], o_data_s[11:8],  i_data_a[11:8],  i_data_b[11:8],  m_data_c[1]);
	cla_block u_cla_block4( m_data_c[3], o_data_s[15:12], i_data_a[15:12], i_data_b[15:12], m_data_c[2]);
	cla_block u_cla_block5( m_data_c[4], o_data_s[19:16], i_data_a[19:16], i_data_b[19:16], m_data_c[3]);
	cla_block u_cla_block6( m_data_c[5], o_data_s[23:20], i_data_a[23:20], i_data_b[23:20], m_data_c[4]);
	cla_block u_cla_block7( m_data_c[6], o_data_s[27:24], i_data_a[27:24], i_data_b[27:24], m_data_c[5]);
	cla_block u_cla_block8( o_carry,     o_data_s[31:28], i_data_a[31:28], i_data_b[31:28], m_data_c[6]);
`endif

endmodule

module cla_block
(
	output				o_carry,
	output	[3:0]		o_data_s,
	input	[3:0]		i_data_a,
	input	[3:0]		i_data_b,
	input				i_carry
);
	wire	[2:0]		m_data_c;
	wire	[3:0]		g;
	wire	[3:0]		p;

	assign g[0]		= i_data_a[0] & i_data_b[0];
	assign g[1]		= i_data_a[1] & i_data_b[1];
	assign g[2]		= i_data_a[2] & i_data_b[2];
	assign g[3]		= i_data_a[3] & i_data_b[3];

	assign p[0]		= i_data_a[0] | i_data_b[0];
	assign p[1]		= i_data_a[1] | i_data_b[1];
	assign p[2]		= i_data_a[2] | i_data_b[2];
	assign p[3]		= i_data_a[3] | i_data_b[3];

	assign m_data_c[0]		= g[0] | (p[0] & i_carry);
	assign m_data_c[1]		= g[1] | (p[1] & m_data_c[0]);
	assign m_data_c[2]		= g[2] | (p[2] & m_data_c[1]);
	assign o_carry			= g[3] | (p[3] & m_data_c[2]);

	assign o_data_s[0]		= (i_data_a[0] ^ i_data_b[0]) ^ i_carry;
	assign o_data_s[1]		= (i_data_a[1] ^ i_data_b[1]) ^ m_data_c[0];
	assign o_data_s[2]		= (i_data_a[2] ^ i_data_b[2]) ^ m_data_c[1];
	assign o_data_s[3]		= (i_data_a[3] ^ i_data_b[3]) ^ m_data_c[2];


endmodule

module compare_adder
#(
	parameter	BIT		= 32
)
(
	output	[BIT-1:0]		o_data_s,
	output					o_carry,
	input	[BIT-1:0]		i_data_a,
	input	[BIT-1:0]		i_data_b,
	input					i_carry
);

	assign {o_carry, o_data_s} = i_data_a + i_data_b + i_carry;

endmodule

project_0/03_adder_cla/carry_lookahead_adder_tb.v
`define CLKFREQ		100
`define SIMCYCLE	10
`define BIT			32
`define VEC			10

`include "carry_lookahead_adder.v"

`define GENER
module carry_lookahead_adder_tb;

// ==================================================================
// DUT Signals & Instantiation
// ==================================================================
	wire	[`BIT-1:0]	o_data_s;
	wire				o_carry;
	reg		[`BIT-1:0]	i_data_a;
	reg		[`BIT-1:0]	i_data_b;
	reg					i_carry;
	reg					i_clk;

	carry_lookahead_adder
	#(
		.BIT		(`BIT)
	)
	u_carry_lookahead_adder
	(
		.o_data_s	(o_data_s	),
		.o_carry	(o_carry	),
		.i_data_a	(i_data_a	),
		.i_data_b	(i_data_b	),
		.i_carry	(i_carry	)
	);

	wire	[31:0]	o_data_s_comp;
	wire			o_carry_comp;

	compare_adder
	#(
		.BIT		(`BIT)
	)
	u_compare_adder
	(
		.o_data_s	(o_data_s_comp	),
		.o_carry	(o_carry_comp	),
		.i_data_a	(i_data_a     	),
		.i_data_b	(i_data_b     	),
		.i_carry	(i_carry     	)
	);

// ==================================================================
// TestVector
// ==================================================================
	reg		[`BIT:0]	vo_data_s	[0:`VEC-1];
	reg		  	 		vo_carry	[0:`VEC-1];
	reg		[`BIT:0]	vi_data_a	[0:`VEC-1];
	reg		[`BIT:0]	vi_data_b	[0:`VEC-1];
	reg					vi_carry	[0:`VEC-1];

	initial begin
		$readmemb("./vec_test/o_data.vec",		vo_data_s);
		$readmemb("./vec_test/o_carry.vec",		vo_carry);
		$readmemb("./vec_test/i_data_a.vec",	vi_data_a);
		$readmemb("./vec_test/i_data_b.vec",	vi_data_b);
		$readmemb("./vec_test/i_carry.vec",		vi_carry);
	end

// ==================================================================
// Clock
// ==================================================================
	always	#(500/`CLKFREQ)		i_clk = ~i_clk;

// ==================================================================
// Task
// ==================================================================
	reg [8*32-1:0] 	taskState;
	reg 			err;

	task init;
		begin			
			taskState	= "Init";
			i_data_a	=	0;
			i_data_b	=	0;
			i_carry		=	0;
			err			=	0;
			i_clk		=	0;
			@(posedge i_clk);
		end
	endtask

	task vecInsert;
		input	[$clog2(`VEC)-1:0]	i;
		begin
			$sformat(taskState,	"VEC[%3d]", i);
			i_data_a		= vi_data_a[i];
			i_data_b		= vi_data_b[i];
			i_carry			= vi_carry[i];
		end
	endtask

	task vecVerify;
		input	[$clog2(`VEC)-1:0]	i;
		begin
			#(0.1*1000/`CLKFREQ);
			if (o_data_s	!= vo_data_s[i]) begin $display("[Idx: %3d] Mismatched o_data_s", i); end
			if (o_carry		!= vo_carry[i]) begin $display("[Idx: %3d] Mismatched o_carry", i); end
			if ((o_data_s != vo_data_s[i]) || (o_carry != vo_carry[i])) begin err++; end
			#(0.9*1000/`CLKFREQ);
		end
	endtask

// ==================================================================
// Test Stimulus
// ==================================================================
	integer	i;
	initial begin
		init();
		
		for (i=0; i<`SIMCYCLE; i++) begin
			vecInsert(i);
			vecVerify(i);	
		end

		repeat(2) @(posedge i_clk);
		$finish;
	end

// ==================================================================
// Dump VCD
// ==================================================================
	reg [8*32-1:0] vcd_file;
	initial begin
		if($value$plusargs("vcd_file=%s", vcd_file)) begin
			$dumpfile(vcd_file);
			$dumpvars;
		end else begin
			$dumpfile("carry_lookahead_adder.vcd");
			$dumpvars;
		end
	end


endmodule

project_0/03_adder_cla/vcd/carry_lookahead_adder.vcd
$date
	Mon Jul  8 17:26:29 2024
$end
$version
	Icarus Verilog
$end
$timescale
	1s
$end
$scope module carry_lookahead_adder_tb $end
$var wire 32 ! o_data_s_comp [31:0] $end
$var wire 32 " o_data_s [31:0] $end
$var wire 1 # o_carry_comp $end
$var wire 1 $ o_carry $end
$var reg 1 % err $end
$var reg 1 & i_carry $end
$var reg 1 ' i_clk $end
$var reg 32 ( i_data_a [31:0] $end
$var reg 32 ) i_data_b [31:0] $end
$var reg 256 * taskState [255:0] $end
$var reg 256 + vcd_file [255:0] $end
$var integer 32 , i [31:0] $end
$scope module u_carry_lookahead_adder $end
$var wire 1 & i_carry $end
$var wire 32 - i_data_a [31:0] $end
$var wire 32 . i_data_b [31:0] $end
$var wire 32 / o_data_s [31:0] $end
$var wire 1 $ o_carry $end
$var wire 8 0 m_data_c [7:0] $end
$scope module u_cla_block1 $end
$var wire 1 & i_carry $end
$var wire 4 1 i_data_a [3:0] $end
$var wire 4 2 i_data_b [3:0] $end
$var wire 1 3 o_carry $end
$var wire 4 4 p [3:0] $end
$var wire 4 5 o_data_s [3:0] $end
$var wire 3 6 m_data_c [2:0] $end
$var wire 4 7 g [3:0] $end
$upscope $end
$scope module u_cla_block2 $end
$var wire 1 8 i_carry $end
$var wire 4 9 i_data_a [3:0] $end
$var wire 4 : i_data_b [3:0] $end
$var wire 1 ; o_carry $end
$var wire 4 < p [3:0] $end
$var wire 4 = o_data_s [3:0] $end
$var wire 3 > m_data_c [2:0] $end
$var wire 4 ? g [3:0] $end
$upscope $end
$scope module u_cla_block3 $end
$var wire 1 @ i_carry $end
$var wire 4 A i_data_a [3:0] $end
$var wire 4 B i_data_b [3:0] $end
$var wire 1 C o_carry $end
$var wire 4 D p [3:0] $end
$var wire 4 E o_data_s [3:0] $end
$var wire 3 F m_data_c [2:0] $end
$var wire 4 G g [3:0] $end
$upscope $end
$scope module u_cla_block4 $end
$var wire 1 H i_carry $end
$var wire 4 I i_data_a [3:0] $end
$var wire 4 J i_data_b [3:0] $end
$var wire 1 K o_carry $end
$var wire 4 L p [3:0] $end
$var wire 4 M o_data_s [3:0] $end
$var wire 3 N m_data_c [2:0] $end
$var wire 4 O g [3:0] $end
$upscope $end
$scope module u_cla_block5 $end
$var wire 1 P i_carry $end
$var wire 4 Q i_data_a [3:0] $end
$var wire 4 R i_data_b [3:0] $end
$var wire 1 S o_carry $end
$var wire 4 T p [3:0] $end
$var wire 4 U o_data_s [3:0] $end
$var wire 3 V m_data_c [2:0] $end
$var wire 4 W g [3:0] $end
$upscope $end
$scope module u_cla_block6 $end
$var wire 1 X i_carry $end
$var wire 4 Y i_data_a [3:0] $end
$var wire 4 Z i_data_b [3:0] $end
$var wire 1 [ o_carry $end
$var wire 4 \ p [3:0] $end
$var wire 4 ] o_data_s [3:0] $end
$var wire 3 ^ m_data_c [2:0] $end
$var wire 4 _ g [3:0] $end
$upscope $end
$scope module u_cla_block7 $end
$var wire 1 ` i_carry $end
$var wire 4 a i_data_a [3:0] $end
$var wire 4 b i_data_b [3:0] $end
$var wire 1 c o_carry $end
$var wire 4 d p [3:0] $end
$var wire 4 e o_data_s [3:0] $end
$var wire 3 f m_data_c [2:0] $end
$var wire 4 g g [3:0] $end
$upscope $end
$scope module u_cla_block8 $end
$var wire 1 h i_carry $end
$var wire 4 i i_data_a [3:0] $end
$var wire 4 j i_data_b [3:0] $end
$var wire 1 $ o_carry $end
$var wire 4 k p [3:0] $end
$var wire 4 l o_data_s [3:0] $end
$var wire 3 m m_data_c [2:0] $end
$var wire 4 n g [3:0] $end
$upscope $end
$upscope $end
$scope module u_compare_adder $end
$var wire 1 & i_carry $end
$var wire 32 o i_data_a [31:0] $end
$var wire 32 p i_data_b [31:0] $end
$var wire 32 q o_data_s [31:0] $end
$var wire 1 # o_carry $end
$upscope $end
$scope task init $end
$upscope $end
$scope task vecInsert $end
$var reg 4 r i [3:0] $end
$upscope $end
$scope task vecVerify $end
$var reg 4 s i [3:0] $end
$upscope $end
$upscope $end
$enddefinitions $end
#0
$dumpvars
bx s
bx r
b0 q
b0 p
b0 o
b0 n
b0 m
b0 l
b0 k
b0 j
b0 i
0h
b0 g
b0 f
b0 e
b0 d
0c
b0 b
b0 a
0`
b0 _
b0 ^
b0 ]
b0 \
0[
b0 Z
b0 Y
0X
b0 W
b0 V
b0 U
b0 T
0S
b0 R
b0 Q
0P
b0 O
b0 N
b0 M
b0 L
0K
b0 J
b0 I
0H
b0 G
b0 F
b0 E
b0 D
0C
b0 B
b0 A
0@
b0 ?
b0 >
b0 =
b0 <
0;
b0 :
b0 9
08
b0 7
b0 6
b0 5
b0 4
03
b0 2
b0 1
bz0000000 0
b0 /
b0 .
b0 -
bx ,
b101110001011110111011001100011011001000010111101100011011000010111001001110010011110010101111101101100011011110110111101101011011000010110100001100101011000010110010001011111011000010110010001100100011001010111001000101110011101100110001101100100 +
b1001001011011100110100101110100 *
b0 )
b0 (
0'
0&
0%
0$
0#
b0 "
b0 !
$end
#5
b111 N
1$
18
1@
1H
1h
b1 6
13
b111 >
1;
1C
b10 f
bz1000111 0
1c
b100 m
b111 E
b1000 M
b101 e
b1100 =
b110 U
b11 ]
b11 l
b111 L
b1001 7
b1101 4
b1100 ?
b1111 <
b1000 G
b1110 D
b110 T
b11 \
b1010 g
b1011 d
b100 n
b1110 k
b110101001101101000011111000111 "
b110101001101101000011111000111 /
b111 5
b1101 2
b1100 :
b1110 B
b111 J
b100 R
b1 Z
b1011 b
b110 j
1#
b1001 1
b1111 9
b1000 A
b10 Q
b10 Y
b1010 a
b1100 i
b110101001101101000011111000111 !
b110101001101101000011111000111 q
b0 s
1&
b1101011000101000111111011001101 )
b1101011000101000111111011001101 .
b1101011000101000111111011001101 p
b11001010001000100000100011111001 (
b11001010001000100000100011111001 -
b11001010001000100000100011111001 o
b101011001000101010000110101101100100000001000000011000001011101 *
b0 r
b0 ,
1'
#10
0'
#15
1X
1S
1P
b110 N
1K
b11 6
b110 >
1`
1h
b111 f
b111 m
b111 V
b11 F
b100 ^
1[
bz1111111 0
1c
b101 E
b101 5
b1 =
b1 M
b10 U
b1001 ]
b10 e
b1000010100100100001010100010101 "
b1000010100100100001010100010101 /
b100 l
b1110 L
b10 W
b1011 4
b10 ?
b1110 <
b1001 G
b1011 D
b10 O
b1111 T
b1100 _
b1100 \
b10 g
b1111 d
b1111 k
b1001 2
b110 :
b1001 B
b1110 J
b11 R
b1100 Z
b1010 b
b1011 1
b1010 9
b1011 A
b10 I
b1110 Q
b1100 Y
b111 a
b1101 i
b1000010100100100001010100010101 !
b1000010100100100001010100010101 q
1'
b1 s
b1101010110000111110100101101001 )
b1101010110000111110100101101001 .
b1101010110000111110100101101001 p
b11010111110011100010101110101011 (
b11010111110011100010101110101011 -
b11010111110011100010101110101011 o
b101011001000101010000110101101100100000001000000011000101011101 *
b1 r
b1 ,
#20
0'
#25
b111 f
b10 e
1`
1[
0P
0X
18
0K
b1 m
b111 6
b1 F
b0 V
0S
0$
bz1100111 0
13
b101 >
b1 N
b110 ^
b110 M
b11 5
b10 =
b11 E
b11 U
b1 ]
b1100010000100110110001100100011 "
b1100010000100110110001100100011 /
b110 l
b11 7
b0 W
b1111 4
b100 ?
b1101 <
b1001 D
b0 O
b101 L
b11 T
b10 _
b1111 \
b0 n
b101 k
b11 2
b101 :
b101 J
b0 R
b110 Z
b1110 b
b101 j
b1111 1
b1100 9
b1001 A
b0 I
b11 Q
b1011 Y
b11 a
b0 i
b1100010000100110110001100100011 !
b1100010000100110110001100100011 q
0#
1'
b10 s
b1011110011000000101100101010011 )
b1011110011000000101100101010011 .
b1011110011000000101100101010011 p
b11101100110000100111001111 (
b11101100110000100111001111 -
b11101100110000100111001111 o
b101011001000101010000110101101100100000001000000011001001011101 *
b10 r
b10 ,
#30
0'
#35
0h
0c
b1 V
1P
1K
0@
0;
1H
b0 f
b0 >
b100 F
bz0101101 0
1C
b100 N
b100 ^
b111 =
b10 E
b11 M
b1110 U
b1 ]
b1111 e
b10 l
b0 ?
b0 g
b1 k
b101 7
b110 <
b100 G
b1110 D
b100 O
b1110 L
b1101 T
b100 _
b1101 \
b1110 d
b1 n
b101111000111100011001001110100 "
b101111000111100011001001110100 /
b100 5
b1111 2
b0 :
b1100 B
b110 J
b1100 R
b1101 Z
b1000 b
b1 j
b101 1
b110 9
b110 A
b1100 I
b1 Q
b100 Y
b110 a
b1 i
b101111000111100011001001110100 !
b101111000111100011001001110100 q
1'
b11 s
0&
b11000110111000110110000001111 )
b11000110111000110110000001111 .
b11000110111000110110000001111 p
b10110010000011100011001100101 (
b10110010000011100011001100101 -
b10110010000011100011001100101 o
b101011001000101010000110101101100100000001000000011001101011101 *
b11 r
b11 ,
#40
0'
#45
0H
0C
08
0`
b1010 l
03
0[
b0 >
b100 N
1X
b110 6
b1 F
b110 V
bz0011000 0
1S
b111 ^
b111 f
b101 m
1$
b1010 e
b1001 5
b1001 =
b1110 E
b1 M
b1001 U
b10101010100110010001111010011001 "
b10101010100110010001111010011001 /
b1001 ]
b111 4
b10 7
b1001 <
b1 G
b1101 D
b1101 L
b1010 W
b1110 T
b1 _
b111 \
b11 g
b111 d
b1101 n
b1101 k
b111 2
b1101 B
b100 J
b1110 R
b1 Z
b111 b
b1101 j
1#
b10 1
b1001 9
b1 A
b1101 I
b1010 Q
b111 Y
b11 a
b1101 i
b10101010100110010001111010011001 !
b10101010100110010001111010011001 q
1'
b100 s
b11010111000111100100110100000111 )
b11010111000111100100110100000111 .
b11010111000111100100110100000111 p
b11010011011110101101000110010010 (
b11010011011110101101000110010010 -
b11010011011110101101000110010010 o
b101011001000101010000110101101100100000001000000011010001011101 *
b100 r
b100 ,
#50
0'
#55
0$
0P
1@
18
0K
b11 ^
1h
1;
13
b111 >
b1 F
b0 N
b100 V
b0 f
bz1010011 0
1c
b0 m
b1110 =
b110 e
b1111 l
b1110 E
b11 M
b11 U
b110 ]
b10 _
b1101 7
b1111 4
b1110 ?
b1111 <
b0 G
b0 O
b11 L
b100 W
b1111 T
b11 \
b1000 g
b1110 d
b0 n
b1110 k
b111 6
b11110110011000110011111011101101 "
b11110110011000110011111011101101 /
b1101 5
b1111 2
b1111 :
b101 B
b1 J
b10 Z
b1100 b
b10 j
0#
b1101 1
b1110 9
b1000 A
b10 I
b101 Q
b11 Y
b1010 a
b1100 i
b11110110011000110011111011101101 !
b11110110011000110011111011101101 q
1'
b101 s
1&
b101100001011100001010111111111 )
b101100001011100001010111111111 .
b101100001011100001010111111111 p
b11001010001101010010100011101101 (
b11001010001101010010100011101101 -
b11001010001101010010100011101101 o
b101011001000101010000110101101100100000001000000011010101011101 *
b101 r
b101 ,
#60
0'
#65
b1 N
1H
1C
b10 ^
0X
0S
0@
1$
b0 6
b11 >
bz1000101 0
0;
b111 F
b0 V
b111 f
b111 m
b101 =
b10 E
b1010 M
b111 U
b1101 ]
b1110 e
b1010 l
b111 T
b1000 7
b1010 4
b1 ?
b11 <
b11 G
b1111 D
b1001 L
b0 W
b1011 \
b1111 g
b1111 d
b1010 n
b1111 k
b10101110110101111010001001010010 "
b10101110110101111010001001010010 /
b10 5
b1010 2
b1 :
b111 B
b101 R
b11 Z
b1111 b
b1110 j
1#
b1000 1
b11 9
b1011 A
b1000 I
b10 Q
b1010 Y
b1111 a
b1011 i
b10101110110101111010001001010010 !
b10101110110101111010001001010010 q
1'
b110 s
0&
b11101111001101010001011100011010 )
b11101111001101010001011100011010 .
b11101111001101010001011100011010 p
b10111111101000101000101100111000 (
b10111111101000101000101100111000 -
b10111111101000101000101100111000 o
b101011001000101010000110101101100100000001000000011011001011101 *
b110 r
b110 ,
#70
0'
#75
0$
0H
b100 e
18
0C
b111 N
bz1000001 0
13
b100 6
b0 >
b1 F
b100 V
b0 ^
b10 f
b1 m
b10 5
b101 =
b10 E
b1000 M
b1010 U
b101 ]
b10100100010110101000001001010010 "
b10100100010110101000001001010010 /
b1010 l
b110 T
b100 7
b1110 4
b0 ?
b100 <
b1 G
b1 D
b1 O
b111 L
b100 W
b0 _
b101 \
b1010 g
b1010 d
b0 n
b1001 k
b110 2
b0 :
b1 B
b101 J
b100 R
b100 Z
b1010 b
b1001 j
b1100 1
b100 9
b1 A
b11 I
b110 Q
b1 Y
b1010 a
b0 i
b10100100010110101000001001010010 !
b10100100010110101000001001010010 q
0#
1'
b111 s
b10011010010001000101000100000110 )
b10011010010001000101000100000110 .
b10011010010001000101000100000110 p
b1010000101100011000101001100 (
b1010000101100011000101001100 -
b1010000101100011000101001100 o
b101011001000101010000110101101100100000001000000011011101011101 *
b111 r
b111 ,
#80
0'
#85
1@
1;
1$
08
1`
03
1[
0P
bz1100010 0
0K
b111 m
b0 V
b0 6
b111 >
b111 F
b0 N
b100 ^
b101 f
b1011 E
b110 U
b1010 e
b0 =
b1000 M
b11 ]
b0 l
b0 W
b0 7
b1 ?
b1111 <
b11 G
b111 D
b0 O
b1000 L
b100 _
b1111 \
b1100 g
b1101 d
b1111 k
b1010001101101000101100001111 "
b1010001101101000101100001111 /
b1111 5
b101 :
b111 B
b1000 J
b0 R
b111 Z
b1101 b
b0 j
b1000 1
b1011 9
b11 A
b0 I
b1100 Y
b1100 a
b1111 i
b1010001101101000101100001111 !
b1010001101101000101100001111 q
1#
1'
b1000 s
1&
b1101011100001000011101010110 )
b1101011100001000011101010110 .
b1101011100001000011101010110 p
b11111100110001100000001110111000 (
b11111100110001100000001110111000 -
b11111100110001100000001110111000 o
b101011001000101010000110101101100100000001000000011100001011101 *
b1000 r
b1000 ,
#90
0'
#95
0@
0;
0h
0c
0H
0C
1P
1X
b0 m
b0 >
b110 V
b100 6
b0 F
1K
bz0111000 0
1S
b1 ^
b1 f
b1111 =
b1001 U
b1010 e
b1110 E
b0 M
b111 ]
b100 l
b0 ?
b1101 \
b1000 n
b100 7
b111 4
b0 G
b1110 D
b1000 O
b1010 W
b1110 T
b1001 _
b0 g
b1001 d
b1100 k
b1001010011110010000111011111011 "
b1001010011110010000111011111011 /
b1011 5
b100 :
b100 B
b1110 R
b1101 Z
b0 b
b1000 j
b101 1
b1010 A
b1000 I
b1010 Q
b1001 Y
b1001 a
b1100 i
b1001010011110010000111011111011 !
b1001010011110010000111011111011 q
1'
b1001 s
0&
b10000000110111101000010001000110 )
b10000000110111101000010001000110 .
b10000000110111101000010001000110 p
b11001001100110101000101010110101 (
b11001001100110101000101010110101 -
b11001001100110101000101010110101 o
b101011001000101010000110101101100100000001000000011100101011101 *
b1001 r
b1001 ,
#100
0'
#105
1'
b1010 ,
