1.combination/full_addr/adder_4bit.v
`include "fa.v"

module adder_4bit
(
	output	[3:0]	o_s,
	output			o_c,
	input	[3:0]	i_a,
	input	[3:0]	i_b,
	input			i_c
);

	wire	[2:0]	carry;


	fa
	u_fa0(
		.o_s	(o_s[0]		),
		.o_c	(carry[0]	),
		.i_a	(i_a[0]		),
		.i_b	(i_b[0]		),
		.i_c	(i_c		)
	);

	fa
	u_fa1(
		.o_s	(o_s[1]		),
		.o_c	(carry[1]	),
		.i_a	(i_a[1]		),
		.i_b	(i_b[1]		),
		.i_c	(carry[0]	)
	);
																																																					
	fa
	u_fa2(
		.o_s	(o_s[2]		),
		.o_c	(carry[2]	),
		.i_a	(i_a[2]		),
		.i_b	(i_b[2]		),
		.i_c	(carry[1]	)
	);

	fa
	u_fa3(
		.o_s	(o_s[3]		),
		.o_c	(o_c		),
		.i_a	(i_a[3]		),
		.i_b	(i_b[3]		),
		.i_c	(carry[2]	)
	);

endmodule		


module adder_4bit_dataflow
(
	output	[3:0]	o_s,
	output			o_c,
	input	[3:0]	i_a,
	input	[3:0]	i_b,
	input			i_c
);

	assign	{o_c, o_s}	= i_a + i_b + i_c;
	
endmodule

1.combination/full_addr/fa.v
module fa
(
	output		o_s,
	output		o_c,
	input		i_a,
	input		i_b,
	input		i_c
);

	assign {o_c, o_s}	= i_a + i_b + i_c;

endmodule

1.combination/full_addr/adder_4bit_tb.v
`define CLKFREQ		100
`define SIMCYCLE	100

`include "adder_4bit.v"

module adder_4bit_tb;

// ========================================
// DUT Signals & Instantiation
// ========================================
	wire	[3:0]	o_s;
	wire			o_c;
	reg		[3:0]	i_a;
	reg		[3:0]	i_b;
	reg				i_c;

	adder_4bit
	u_adder_4bit
	(
		.o_s    (o_s),
		.o_c    (o_c),
		.i_a    (i_a),
		.i_b    (i_b),
		.i_c    (i_c)
	);

																																																			
	adder_4bit_dataflow
	u_adder_4bit_dataflow
	(
		.o_s    (o_s),
		.o_c    (o_c),
		.i_a    (i_a),
		.i_b    (i_b),
		.i_c    (i_c)
	);


// ========================================
// Test Stimulus
// ========================================
integer i;
initial begin

	for(i=0; i<`SIMCYCLE; i++) begin
		i_a	= $random;
		i_b	= $random;
		i_c	= $random;
		#(1000/`CLKFREQ);
    end	
	#(1000/`CLKFREQ);
    $finish;
end

// ========================================
// Dump VCD
// ========================================
reg [8*32-1:0] vcd_file;
initial begin
	if($value$plusargs("vcd_file=%s", vcd_file)) begin
		$dumpfile(vcd_file);
		$dumpvars;
	end else begin
		$dumpfile("adder_4bit_tb.vcd");
		$dumpvars;
	end
end
endmodule

1.combination/full_addr/vcd/adder_4bit.vcd
$date
	Thu Jun 27 21:00:58 2024
$end
$version
	Icarus Verilog
$end
$timescale
	1s
$end
$scope module adder_4bit_tb $end
$var wire 1 ! o_c $end
$var wire 4 " o_s [3:0] $end
$var reg 4 # i_a [3:0] $end
$var reg 4 $ i_b [3:0] $end
$var reg 1 % i_c $end
$var reg 256 & vcd_file [255:0] $end
$var integer 32 ' i [31:0] $end
$scope module u_adder_4bit $end
$var wire 4 ( i_a [3:0] $end
$var wire 4 ) i_b [3:0] $end
$var wire 1 % i_c $end
$var wire 1 ! o_c $end
$var wire 4 * o_s [3:0] $end
$var wire 3 + carry [2:0] $end
$scope module u_fa0 $end
$var wire 1 , i_a $end
$var wire 1 - i_b $end
$var wire 1 % i_c $end
$var wire 1 . o_s $end
$var wire 1 / o_c $end
$upscope $end
$scope module u_fa1 $end
$var wire 1 0 i_a $end
$var wire 1 1 i_b $end
$var wire 1 2 i_c $end
$var wire 1 3 o_s $end
$var wire 1 4 o_c $end
$upscope $end
$scope module u_fa2 $end
$var wire 1 5 i_a $end
$var wire 1 6 i_b $end
$var wire 1 7 i_c $end
$var wire 1 8 o_s $end
$var wire 1 9 o_c $end
$upscope $end
$scope module u_fa3 $end
$var wire 1 : i_a $end
$var wire 1 ; i_b $end
$var wire 1 < i_c $end
$var wire 1 ! o_c $end
$var wire 1 = o_s $end
$upscope $end
$upscope $end
$scope module u_adder_4bit_dataflow $end
$var wire 4 > i_a [3:0] $end
$var wire 4 ? i_b [3:0] $end
$var wire 1 % i_c $end
$var wire 1 ! o_c $end
$var wire 4 @ o_s [3:0] $end
$upscope $end
$upscope $end
$enddefinitions $end
#0
$dumpvars
b110 @
b1 ?
b100 >
0=
0<
0;
0:
09
18
07
06
15
04
13
12
01
00
1/
0.
1-
0,
b1 +
b110 *
b1 )
b100 (
b0 '
b10111000101111011101100110001101100100001011110110000101100100011001000110010101110010010111110011010001100010011010010111010000101110011101100110001101100100 &
1%
b1 $
b100 #
b110 "
0!
$end
#10
1<
08
19
17
0=
1.
03
b111 +
14
16
1;
1!
1,
10
05
b1 "
b1 *
b1 @
b1101 $
b1101 )
b1101 ?
b11 #
b11 (
b11 >
b1 '
#20
0.
1=
0-
11
06
0;
0!
00
15
b1000 "
b1000 *
b1000 @
b10 $
b10 )
b10 ?
b101 #
b101 (
b101 >
b10 '
#30
18
0=
16
1:
b100 "
b100 *
b100 @
1!
b110 $
b110 )
b110 ?
b1101 #
b1101 (
b1101 >
b11 '
#40
08
07
13
b101 +
04
1=
01
1;
b1010 "
b1010 *
b1010 @
b1100 $
b1100 )
b1100 ?
b100 '
#50
08
07
02
13
04
1.
b100 +
0/
1-
0;
0!
0,
10
0:
b1011 "
b1011 *
b1011 @
0%
b101 $
b101 )
b101 ?
b110 #
b110 (
b110 >
b101 '
#60
18
17
03
14
12
0.
b111 +
1/
11
1,
00
b1100 "
b1100 *
b1100 @
b111 $
b111 )
b111 ?
b101 #
b101 (
b101 >
b110 '
#70
02
1.
b110 +
0/
08
03
0=
0-
06
10
1:
b1 "
b1 *
b1 @
1!
b10 $
b10 )
b10 ?
b1111 #
b1111 (
b1111 >
b111 '
#80
1=
0<
18
09
07
b0 +
04
1-
01
16
0,
00
05
b1101 "
b1101 *
b1101 @
0!
b101 $
b101 )
b101 ?
b1000 #
b1000 (
b1000 >
b1000 '
#90
13
1<
12
1=
08
19
b101 +
1/
1;
1,
15
b1011 "
b1011 *
b1011 @
1!
1%
b1101 $
b1101 )
b1101 ?
b1101 #
b1101 (
b1101 >
b1001 '
#100
03
18
02
17
0<
0/
14
b10 +
09
1=
0-
11
06
0!
10
05
0:
b1101 "
b1101 *
b1101 @
0%
b1010 $
b1010 )
b1010 ?
b11 #
b11 (
b11 >
b1010 '
#110
08
07
13
b0 +
04
0,
00
b1011 "
b1011 *
b1011 @
1%
b0 #
b0 (
b0 >
b1011 '
#120
1<
19
12
17
0.
1/
1=
13
b111 +
14
08
1-
0;
10
15
b1010 "
b1010 *
b1010 @
b11 $
b11 )
b11 ?
b110 #
b110 (
b110 >
b1100 '
#130
0<
1=
0!
1.
18
b11 +
09
1;
1,
05
b1111 "
b1111 *
b1111 @
b1011 $
b1011 )
b1011 ?
b11 #
b11 (
b11 >
b1101 '
#140
03
0=
02
1<
0/
08
b110 +
19
0-
16
1!
0,
b1 "
b1 *
b1 @
b1110 $
b1110 )
b1110 ?
b10 #
b10 (
b10 >
b1110 '
#150
13
12
b111 +
1/
0.
1-
06
0;
1,
15
1:
b10 "
b10 *
b10 @
0%
b11 $
b11 )
b11 ?
b1111 #
b1111 (
b1111 >
b1111 '
#160
0<
18
09
07
04
02
13
0=
b0 +
0/
0-
01
16
1;
0,
05
b110 "
b110 *
b110 @
b1100 $
b1100 )
b1100 ?
b1010 #
b1010 (
b1010 >
b10000 '
#170
1.
08
1=
1-
06
0;
b1011 "
b1011 *
b1011 @
0!
b1 $
b1 )
b1 ?
b10001 '
#180
12
0=
13
0.
b1 +
1/
1;
1!
00
b10 "
b10 *
b10 @
1%
b1001 $
b1001 )
b1001 ?
b1000 #
b1000 (
b1000 >
b10010 '
#190
1=
18
03
1<
17
02
19
14
b110 +
0/
0-
11
16
0;
0!
10
15
0:
b1100 "
b1100 *
b1100 @
0%
b110 $
b110 )
b110 ?
b110 #
b110 (
b110 >
b10011 '
#200
0=
0<
09
07
18
13
b0 +
04
1.
06
1;
00
1:
b111 "
b111 *
b111 @
1!
1%
b1010 $
b1010 )
b1010 ?
b1100 #
b1100 (
b1100 >
b10100 '
#210
12
b111 "
b111 *
b111 @
13
b1 +
1/
1-
01
16
0;
1,
05
0:
0!
b101 $
b101 )
b101 ?
b1 #
b1 (
b1 >
b10101 '
#220
03
02
17
0/
18
b10 +
14
0-
11
06
1;
10
1:
b101 "
b101 *
b101 @
1!
0%
b1010 $
b1010 )
b1010 ?
b1011 #
b1011 (
b1011 >
b10110 '
#230
0=
13
07
0<
12
04
18
09
b1 +
1/
1-
01
0;
00
15
0:
b111 "
b111 *
b111 @
0!
1%
b1 $
b1 )
b1 ?
b101 #
b101 (
b101 >
b10111 '
#240
0!
0<
18
09
02
07
0/
1=
13
b0 +
04
0-
16
1;
0,
10
05
b1111 "
b1111 *
b1111 @
b1100 $
b1100 )
b1100 ?
b10 #
b10 (
b10 >
b11000 '
#250
1<
08
19
17
03
14
12
0.
b111 +
1/
1=
06
1,
15
1:
b1000 "
b1000 *
b1000 @
1!
b1000 $
b1000 )
b1000 ?
b1111 #
b1111 (
b1111 >
b11001 '
#260
18
16
b1100 "
b1100 *
b1100 @
b1100 $
b1100 )
b1100 ?
b11010 '
#270
0=
08
0<
07
09
13
b1 +
04
1-
06
00
05
b10 "
b10 *
b10 @
0%
b1001 $
b1001 )
b1001 ?
b1001 #
b1001 (
b1001 >
b11011 '
#280
1=
1<
19
17
03
b111 +
14
08
0;
0!
10
15
0:
b1000 "
b1000 *
b1000 @
b1 $
b1 )
b1 ?
b111 #
b111 (
b111 >
b11100 '
#290
0<
18
09
07
13
04
02
b0 +
0/
1=
0!
0-
11
0,
00
1:
b1110 "
b1110 *
b1110 @
b10 $
b10 )
b10 ?
b1100 #
b1100 (
b1100 >
b11101 '
#300
17
03
14
0=
12
1<
1/
18
b111 +
19
1-
01
16
1;
1!
1,
10
0:
b100 "
b100 *
b100 @
b1101 $
b1101 )
b1101 ?
b111 #
b111 (
b111 >
b11110 '
#310
1=
0,
1:
b1100 "
b1100 *
b1100 @
1%
b1110 #
b1110 (
b1110 >
b11111 '
#320
13
08
0=
1.
11
06
0;
1,
b11 "
b11 *
b11 @
b11 $
b11 )
b11 ?
b1111 #
b1111 (
b1111 >
b100000 '
#330
0<
0=
0.
03
18
b11 +
09
1;
0,
00
05
b100 "
b100 *
b100 @
b1011 $
b1011 )
b1011 ?
b1000 #
b1000 (
b1000 >
b100001 '
#340
1=
1<
02
03
08
19
1.
b110 +
0/
0-
1,
10
15
b1001 "
b1001 *
b1001 @
0%
b1010 $
b1010 )
b1010 ?
b1111 #
b1111 (
b1111 >
b100010 '
#350
18
0.
0=
16
0,
0:
b100 "
b100 *
b100 @
b1110 $
b1110 )
b1110 ?
b110 #
b110 (
b110 >
b100011 '
#360
08
1.
0;
05
1:
b1 "
b1 *
b1 @
1%
b110 $
b110 )
b110 ?
b1010 #
b1010 (
b1010 >
b100100 '
#370
13
12
b111 +
1/
1-
1;
1,
0:
b11 "
b11 *
b11 @
b1111 $
b1111 )
b1111 ?
b11 #
b11 (
b11 >
b100101 '
#380
0.
03
18
0-
01
0;
15
1:
b100 "
b100 *
b100 @
b100 $
b100 )
b100 ?
b1111 #
b1111 (
b1111 >
b100110 '
#390
02
03
08
1.
b110 +
0/
11
05
b1 "
b1 *
b1 @
0%
b110 $
b110 )
b110 ?
b1011 #
b1011 (
b1011 >
b100111 '
#400
0<
13
18
09
12
07
0.
1/
0=
b1 +
04
1-
01
1;
00
b110 "
b110 *
b110 @
b1101 $
b1101 )
b1101 ?
b1001 #
b1001 (
b1001 >
b101000 '
#410
1=
1<
08
b101 +
19
1.
0;
0!
15
0:
b1011 "
b1011 *
b1011 @
1%
b101 $
b101 )
b101 ?
b101 #
b101 (
b101 >
b101001 '
#420
03
02
0<
0/
18
b0 +
09
1=
0!
0-
05
1:
b1101 "
b1101 *
b1101 @
0%
b100 $
b100 )
b100 ?
b1001 #
b1001 (
b1001 >
b101010 '
#430
17
b10 +
14
18
0=
1-
11
06
1;
1!
0,
10
b101 "
b101 *
b101 @
b1011 $
b1011 )
b1011 ?
b1010 #
b1010 (
b1010 >
b101011 '
#440
0=
07
0<
13
04
18
b0 +
09
0-
00
15
b111 "
b111 *
b111 @
1%
b1010 $
b1010 )
b1010 ?
b1100 #
b1100 (
b1100 >
b101100 '
#450
1=
1<
08
19
17
03
b110 +
14
16
0;
1,
10
05
0:
b1001 "
b1001 *
b1001 @
0!
0%
b110 $
b110 )
b110 ?
b11 #
b11 (
b11 >
b101101 '
#460
0=
06
1;
1!
15
b1 "
b1 *
b1 @
b1010 $
b1010 )
b1010 ?
b111 #
b111 (
b111 >
b101110 '
#470
07
0<
04
08
b0 +
09
b1 "
b1 *
b1 @
0=
1-
01
0,
00
05
1:
b1001 $
b1001 )
b1001 ?
b1000 #
b1000 (
b1000 >
b101111 '
#480
13
18
11
0;
15
0:
b111 "
b111 *
b111 @
0!
b11 $
b11 )
b11 ?
b100 #
b100 (
b100 >
b110000 '
#490
17
03
14
12
18
b11 +
1/
1;
1!
1,
05
1:
b101 "
b101 *
b101 @
1%
b1011 $
b1011 )
b1011 ?
b1001 #
b1001 (
b1001 >
b110001 '
#500
0=
07
0<
13
04
18
b1 +
09
0.
01
16
b110 "
b110 *
b110 @
0%
b1101 $
b1101 )
b1101 ?
b110010 '
#510
1<
03
08
19
02
17
0/
0=
1!
b110 +
14
1.
0-
11
0;
0,
10
b1 "
b1 *
b1 @
1%
b110 $
b110 )
b110 ?
b1010 #
b1010 (
b1010 >
b110011 '
#520
07
13
b100 +
04
08
1=
01
15
0:
b1011 "
b1011 *
b1011 @
0!
b100 $
b100 )
b100 ?
b110 #
b110 (
b110 >
b110100 '
#530
0<
03
18
b0 +
09
1=
0!
1,
00
05
1:
b1101 "
b1101 *
b1101 @
0%
b1001 #
b1001 (
b1001 >
b110101 '
#540
13
12
0=
0.
b1 +
1/
1-
1;
1!
0,
b110 "
b110 *
b110 @
1%
b1101 $
b1101 )
b1101 ?
b1000 #
b1000 (
b1000 >
b110110 '
#550
0=
0<
18
09
07
02
b110 "
b110 *
b110 @
13
04
b0 +
0/
0-
06
10
15
0%
b1000 $
b1000 )
b1000 ?
b1110 #
b1110 (
b1110 >
b110111 '
#560
12
b1 +
1/
b110 "
b110 *
b110 @
13
1-
1,
00
b1001 $
b1001 )
b1001 ?
b1101 #
b1101 (
b1101 >
b111000 '
#570
1<
03
08
19
02
17
0/
b110 +
14
0=
1!
1.
0-
11
0,
10
0:
b1 "
b1 *
b1 @
1%
b1010 $
b1010 )
b1010 ?
b110 #
b110 (
b110 >
b111001 '
#580
0<
18
09
07
13
b0 +
04
0=
01
0;
b111 "
b111 *
b111 @
0!
b0 $
b0 )
b0 ?
b111010 '
#590
1=
1<
08
19
17
03
b110 +
14
0.
11
16
1;
1!
05
1:
b1000 "
b1000 *
b1000 @
0%
b1110 $
b1110 )
b1110 ?
b1010 #
b1010 (
b1010 >
b111011 '
#600
1!
1<
08
19
12
17
1/
03
b111 +
14
0=
06
1,
00
15
0:
b0 "
b0 *
b0 @
1%
b1010 $
b1010 )
b1010 ?
b101 #
b101 (
b101 >
b111100 '
#610
02
18
1=
03
1.
b110 +
0/
16
0;
0!
10
b1101 "
b1101 *
b1101 @
0%
b110 $
b110 )
b110 ?
b111 #
b111 (
b111 >
b111101 '
#620
0,
1%
b110 #
b110 (
b110 >
b111110 '
#630
08
07
13
b100 +
04
0=
0.
00
1:
b10 "
b10 *
b10 @
1!
0%
b1100 #
b1100 (
b1100 >
b111111 '
#640
12
1<
17
1/
08
19
1=
13
b111 +
14
1-
06
1;
10
b1010 "
b1010 *
b1010 @
1%
b1011 $
b1011 )
b1011 ?
b1110 #
b1110 (
b1110 >
b1000000 '
#650
0=
0<
03
18
b11 +
09
0-
1,
00
05
b100 "
b100 *
b100 @
b1010 $
b1010 )
b1010 ?
b1001 #
b1001 (
b1001 >
b1000001 '
#660
1=
1<
08
b111 +
19
1-
01
0;
0!
10
15
0:
b1000 "
b1000 *
b1000 @
0%
b1 $
b1 )
b1 ?
b111 #
b111 (
b111 >
b1000010 '
#670
0=
0<
18
09
07
13
b1 +
04
16
0,
00
05
b110 "
b110 *
b110 @
1%
b101 $
b101 )
b101 ?
b0 #
b0 (
b0 >
b1000011 '
#680
08
1.
1=
06
1,
1:
b1011 "
b1011 *
b1011 @
b1 $
b1 )
b1 ?
b1001 #
b1001 (
b1001 >
b1000100 '
#690
18
17
03
b11 +
14
0=
0.
11
1;
1!
0,
b100 "
b100 *
b100 @
b1011 $
b1011 )
b1011 ?
b1000 #
b1000 (
b1000 >
b1000101 '
#700
07
0=
13
04
0<
02
18
09
b0 +
0/
0-
15
b110 "
b110 *
b110 @
0%
b1010 $
b1010 )
b1010 ?
b1100 #
b1100 (
b1100 >
b1000110 '
#710
12
b1 +
1/
13
08
1-
01
05
b10 "
b10 *
b10 @
1%
b1001 $
b1001 )
b1001 ?
b1000 #
b1000 (
b1000 >
b1000111 '
#720
03
18
02
1<
17
1.
0/
19
0=
1!
b110 +
14
0-
11
16
0;
10
15
b101 "
b101 *
b101 @
b110 $
b110 )
b110 ?
b1110 #
b1110 (
b1110 >
b1001000 '
#730
0<
b10 +
09
b101 "
b101 *
b101 @
0=
06
1;
05
b1010 $
b1010 )
b1010 ?
b1010 #
b1010 (
b1010 >
b1001001 '
#740
0=
07
0<
13
04
18
b0 +
09
01
15
b111 "
b111 *
b111 @
b1000 $
b1000 )
b1000 ?
b1110 #
b1110 (
b1110 >
b1001010 '
#750
08
11
00
05
b11 "
b11 *
b11 @
b1010 $
b1010 )
b1010 ?
b1000 #
b1000 (
b1000 >
b1001011 '
#760
1<
19
12
17
1/
08
0=
1!
13
b111 +
14
0.
1-
16
0;
1,
10
b10 "
b10 *
b10 @
0%
b111 $
b111 )
b111 ?
b1011 #
b1011 (
b1011 >
b1001100 '
#770
1=
0<
18
09
07
04
02
b0 +
0/
13
1.
0-
01
0!
0,
b1111 "
b1111 *
b1111 @
1%
b100 $
b100 )
b100 ?
b1010 #
b1010 (
b1010 >
b1001101 '
#780
0=
0:
b111 "
b111 *
b111 @
b10 #
b10 (
b10 >
b1001110 '
#790
1<
08
19
17
03
b110 +
14
0=
0.
11
06
1;
1!
15
b0 "
b0 *
b0 @
0%
b1010 $
b1010 )
b1010 ?
b110 #
b110 (
b110 >
b1001111 '
#800
1=
0<
18
09
07
1.
13
b0 +
04
1-
01
16
05
b1111 "
b1111 *
b1111 @
0!
b1101 $
b1101 )
b1101 ?
b10 #
b10 (
b10 >
b1010000 '
#810
0-
11
06
00
15
1%
b1010 $
b1010 )
b1010 ?
b100 #
b100 (
b100 >
b1010001 '
#820
0=
1<
08
19
17
03
14
12
0.
b111 +
1/
16
1!
1,
05
b0 "
b0 *
b0 @
b1110 $
b1110 )
b1110 ?
b1 #
b1 (
b1 >
b1010010 '
#830
1.
13
1=
1-
10
1:
b1011 "
b1011 *
b1011 @
b1111 $
b1111 )
b1111 ?
b1011 #
b1011 (
b1011 >
b1010011 '
#840
03
0.
18
01
0;
0!
0,
15
0:
b1100 "
b1100 *
b1100 @
b101 $
b101 )
b101 ?
b110 #
b110 (
b110 >
b1010100 '
#850
08
07
0=
13
04
0<
02
09
1.
b0 +
0/
0-
06
1;
1,
05
1:
b11 "
b11 *
b11 @
1!
0%
b1000 $
b1000 )
b1000 ?
b1011 #
b1011 (
b1011 >
b1010101 '
#860
18
17
03
b10 +
14
1=
11
0;
b1101 "
b1101 *
b1101 @
0!
b10 $
b10 )
b10 ?
b1010110 '
#870
12
17
1<
0.
1/
1=
03
14
08
b111 +
19
1-
1;
1!
00
15
b1000 "
b1000 *
b1000 @
b1011 $
b1011 )
b1011 ?
b1101 #
b1101 (
b1101 >
b1010111 '
#880
07
13
04
02
08
1.
b100 +
0/
01
16
0,
10
b1011 "
b1011 *
b1011 @
b1101 $
b1101 )
b1101 ?
b1110 #
b1110 (
b1110 >
b1011000 '
#890
0<
1=
03
b0 +
09
06
0;
0!
00
05
b1001 "
b1001 *
b1001 @
b1 $
b1 )
b1 ?
b1000 #
b1000 (
b1000 >
b1011001 '
#900
18
17
14
12
03
0.
b11 +
1/
11
1;
1,
0:
b1100 "
b1100 *
b1100 @
b1011 $
b1011 )
b1011 ?
b1 #
b1 (
b1 >
b1011010 '
#910
1<
08
b111 +
19
1=
13
0-
16
0;
10
b1010 "
b1010 *
b1010 @
1%
b110 $
b110 )
b110 ?
b11 #
b11 (
b11 >
b1011011 '
#920
0=
0<
18
09
07
04
02
13
1.
b0 +
0/
01
0,
b111 "
b111 *
b111 @
b100 $
b100 )
b100 ?
b10 #
b10 (
b10 >
b1011100 '
#930
08
1=
0.
11
06
00
1:
b1010 "
b1010 *
b1010 @
0%
b10 $
b10 )
b10 ?
b1000 #
b1000 (
b1000 >
b1011101 '
#940
12
13
18
b1 +
1/
1.
1-
01
16
1,
b1111 "
b1111 *
b1111 @
1%
b101 $
b101 )
b101 ?
b1001 #
b1001 (
b1001 >
b1011110 '
#950
17
18
03
b11 +
14
0.
06
10
b1100 "
b1100 *
b1100 @
0%
b1 $
b1 )
b1 ?
b1011 #
b1011 (
b1011 >
b1011111 '
#960
1<
08
b111 +
19
1=
1.
15
0:
b1001 "
b1001 *
b1001 @
1%
b111 #
b111 (
b111 >
b1100000 '
#970
0<
18
09
02
07
1=
0!
0/
03
b0 +
04
0.
0-
1;
0,
00
b1100 "
b1100 *
b1100 @
0%
b1000 $
b1000 )
b1000 ?
b100 #
b100 (
b100 >
b1100001 '
#980
13
0=
11
0;
b110 "
b110 *
b110 @
b10 $
b10 )
b10 ?
b1100010 '
#990
12
13
b1 +
1/
1.
1-
01
16
1,
05
b111 "
b111 *
b111 @
1%
b101 $
b101 )
b101 ?
b1 #
b1 (
b1 >
b1100011 '
#1000
b1100100 '
