project_0/04_shift_register/shift_register.v
module shift_register
(
	output reg	[7:0]	o_parrel,
	output reg			o_serial,
	input				i_serial,
	input		[7:0]	i_parrel,
	input				load,
	input				i_clk,
	input				i_rstn
);
	reg			[7:0]	m_data;

	always @(*) begin
		if(!i_rstn) begin
			o_parrel	<=  8'h0;
			m_data		<=	8'h0;
		end
	end

	always @(posedge i_clk) begin
		if(load == 1)	begin
			m_data		<=  i_parrel;
		end
		else begin
			o_serial	<=  m_data[7];
			m_data		<=  {m_data[6:0], 1'b0};
			o_parrel	<=  {o_parrel[6:0], i_serial};
		end
	end

		
endmodule

project_0/04_shift_register/shift_register_tb.v
`define CLKFREQ		100
`define SIMCYCLE	10

`include "shift_register.v"

module shift_register_tb;

	wire	[7:0]	o_parrel;
	wire			o_serial;
	reg				i_serial;
	reg		[7:0]	i_parrel;
	reg				load;
	reg				i_clk;
	reg				i_rstn;

	shift_register
	u_shift_register
	(
		.o_parrel		(o_parrel),
		.o_serial		(o_serial),
		.i_serial		(i_serial),
		.i_parrel		(i_parrel),
		.load			(load),
		.i_clk			(i_clk),
		.i_rstn			(i_rstn)
	);

	always	#(500/`CLKFREQ)		i_clk = ~i_clk;

	task init;
		begin
			i_serial	=	0;
			i_parrel	=	0;
			load		=	0;
			i_clk		=	0;
			i_rstn		=	0;
			@(posedge i_clk);
		end
	endtask

	integer i;
	task test_load;
		input	[7:0]	data;
		begin
			#1;
			load		= 1'b1;
			i_serial	= data[0];
			i_parrel	= data;
			@(posedge i_clk); #1;
			for (i=0; i<7; i++) begin
			load		= 1'b0;
			i_serial	= data[i+1];
			@(posedge i_clk); #1;
			end
			repeat(2) @(posedge i_clk); #1;
		end
	endtask

	integer j;
	task test_reset;
		begin
			for (j=0; j<8; j++) begin
			i_serial	<= 1'h0;
			@(posedge i_clk);
			end
		end
	endtask

	initial begin
		init();
		
		test_load(8'b0101_0101);	
		test_reset();
		test_load(8'b1100_0011);	
		test_reset();
		test_load(8'b0000_1111);	
		
		$finish;
	end

	reg [8*32-1:0] vcd_file;
	initial begin
		if($value$plusargs("vcd_file=%s", vcd_file)) begin
			$dumpfile(vcd_file);
			$dumpvars;
		end else begin
			$dumpfile("carry_lookahead_adder.vcd");
			$dumpvars;
		end
	end


	endmodule

project_0/04_shift_register/vcd/shift_register.vcd
$date
	Sat Jul  6 21:29:32 2024
$end
$version
	Icarus Verilog
$end
$timescale
	1s
$end
$scope module shift_register_tb $end
$var wire 1 ! o_serial $end
$var wire 8 " o_parrel [7:0] $end
$var reg 1 # i_clk $end
$var reg 8 $ i_parrel [7:0] $end
$var reg 1 % i_rstn $end
$var reg 1 & i_serial $end
$var reg 1 ' load $end
$var reg 256 ( vcd_file [255:0] $end
$var integer 32 ) i [31:0] $end
$var integer 32 * j [31:0] $end
$scope module u_shift_register $end
$var wire 1 # i_clk $end
$var wire 8 + i_parrel [7:0] $end
$var wire 1 % i_rstn $end
$var wire 1 & i_serial $end
$var wire 1 ' load $end
$var reg 8 , m_data [7:0] $end
$var reg 8 - o_parrel [7:0] $end
$var reg 1 ! o_serial $end
$upscope $end
$scope task init $end
$upscope $end
$scope task test_load $end
$var reg 8 . data [7:0] $end
$upscope $end
$scope task test_reset $end
$upscope $end
$upscope $end
$enddefinitions $end
#0
$dumpvars
bx .
b0 -
b0 ,
b0 +
bx *
bx )
b1011100010111101110110011000110110010000101111011100110110100001101001011001100111010001011111011100100110010101100111011010010111001101110100011001010111001000101110011101100110001101100100 (
0'
0&
0%
b0 $
0#
b0 "
x!
$end
#5
0!
b1010101 .
1#
#6
b1010101 $
b1010101 +
1&
1'
#10
0#
#15
b1010101 ,
1#
#16
0&
0'
b0 )
#20
0#
#25
b10101010 ,
1#
#26
1&
b1 )
#30
0#
#35
b1 "
b1 -
b1010100 ,
1!
1#
#36
0&
b10 )
#40
0#
#45
b10 "
b10 -
b10101000 ,
0!
1#
#46
1&
b11 )
#50
0#
#55
b101 "
b101 -
b1010000 ,
1!
1#
#56
0&
b100 )
#60
0#
#65
b1010 "
b1010 -
b10100000 ,
0!
1#
#66
1&
b101 )
#70
0#
#75
b10101 "
b10101 -
b1000000 ,
1!
1#
#76
0&
b110 )
#80
0#
#85
b101010 "
b101010 -
b10000000 ,
0!
1#
#86
b111 )
#90
0#
#95
b1010100 "
b1010100 -
b0 ,
1!
1#
#100
0#
#105
b10101000 "
b10101000 -
0!
1#
#106
b0 *
#110
0#
#115
b1010000 "
b1010000 -
b1 *
1#
#120
0#
#125
b10100000 "
b10100000 -
b10 *
1#
#130
0#
#135
b1000000 "
b1000000 -
b11 *
1#
#140
0#
#145
b10000000 "
b10000000 -
b100 *
1#
#150
0#
#155
b0 "
b0 -
b101 *
1#
#160
0#
#165
b110 *
1#
#170
0#
#175
b111 *
1#
#180
0#
#185
b11000011 .
b1000 *
1#
#186
b11000011 $
b11000011 +
1&
1'
#190
0#
#195
b11000011 ,
1#
#196
0'
b0 )
#200
0#
#205
b1 "
b1 -
b10000110 ,
1!
1#
#206
0&
b1 )
#210
0#
#215
b10 "
b10 -
b1100 ,
1#
#216
b10 )
#220
0#
#225
b100 "
b100 -
b11000 ,
0!
1#
#226
b11 )
#230
0#
#235
b1000 "
b1000 -
b110000 ,
1#
#236
b100 )
#240
0#
#245
b10000 "
b10000 -
b1100000 ,
1#
#246
1&
b101 )
#250
0#
#255
b100001 "
b100001 -
b11000000 ,
1#
#256
b110 )
#260
0#
#265
b1000011 "
b1000011 -
b10000000 ,
1!
1#
#266
b111 )
#270
0#
#275
b10000111 "
b10000111 -
b0 ,
1#
#280
0#
#285
b1111 "
b1111 -
0!
1#
#286
0&
b0 *
#290
0#
#295
b11110 "
b11110 -
b1 *
1#
#300
0#
#305
b111100 "
b111100 -
b10 *
1#
#310
0#
#315
b1111000 "
b1111000 -
b11 *
1#
#320
0#
#325
b11110000 "
b11110000 -
b100 *
1#
#330
0#
#335
b11100000 "
b11100000 -
b101 *
1#
#340
0#
#345
b11000000 "
b11000000 -
b110 *
1#
#350
0#
#355
b10000000 "
b10000000 -
b111 *
1#
#360
0#
#365
b0 "
b0 -
b1111 .
b1000 *
1#
#366
b1111 $
b1111 +
1&
1'
#370
0#
#375
b1111 ,
1#
#376
0'
b0 )
#380
0#
#385
b1 "
b1 -
b11110 ,
1#
#386
b1 )
#390
0#
#395
b11 "
b11 -
b111100 ,
1#
#396
b10 )
#400
0#
#405
b111 "
b111 -
b1111000 ,
1#
#406
0&
b11 )
#410
0#
#415
b1110 "
b1110 -
b11110000 ,
1#
#416
b100 )
#420
0#
#425
b11100 "
b11100 -
b11100000 ,
1!
1#
#426
b101 )
#430
0#
#435
b111000 "
b111000 -
b11000000 ,
1#
#436
b110 )
#440
0#
#445
b1110000 "
b1110000 -
b10000000 ,
1#
#446
b111 )
#450
0#
#455
b11100000 "
b11100000 -
b0 ,
1#
#460
0#
#465
b11000000 "
b11000000 -
0!
1#
