1.combination/dec2/dec2.v
module dec2_behavior
(
	output reg	[3:0]	o_out,
	input		[1:0]	i_in,
	input				i_en
);
																																				
always @(*) begin
	if (i_en == 1'b1) begin
		case(i_in)
			2'b00:	o_out	= 4'b0001;
			2'b01:	o_out	= 4'b0010;
			2'b10:	o_out	= 4'b0100;
			2'b11:	o_out	= 4'b1000;
		endcase
	end else begin
		o_out	= 4'b0;
	end
end

endmodule

module dec2_dataflow
(
	output 		[3:0]	o_out,
	input		[1:0]	i_in,
	input				i_en
);
																																				
	assign o_out	= (i_en == 1'b1) ? (4'd1 << i_in) : 4'd0;

endmodule

1.combination/dec2/dec2_tb.v
`define CLKFREQ		100
`define SIMCYCLE	20

`include "dec2.v"

module dec2_tb;

// ========================================
// DUT Signals & Instantiation
// ========================================
	wire	[3:0]	o_out_f;
	wire	[3:0]	o_out_b;
	reg		[1:0]	i_in;
	reg				i_en;

	dec2_dataflow
	u_dec2_dataflow
	(
		.o_out	(o_out_f),
		.i_in	(i_in),
		.i_en	(i_en)
	);

	dec2_behavior
	u_dec2_behavior
	(
		.o_out	(o_out_b),
		.i_in	(i_in),
		.i_en	(i_en)
	);

// ========================================
// Task
// ========================================
	task init;
		begin
			i_in	= 0;
			i_en	= 0;
		end
	endtask


// ========================================
// Test Stimulus
// ========================================
integer i;
initial begin
	init();

	for(i=0; i<`SIMCYCLE; i++) begin
	{i_in, i_en}	= $urandom_range(0, 2**3-1);
	#(1000 /`CLKFREQ);
    end	
   $finish;
end

// ========================================
// Dump VCD
// ========================================
reg [8*32-1:0] vcd_file;
initial begin
	if($value$plusargs("vcd_file=%s", vcd_file)) begin
		$dumpfile(vcd_file);
		$dumpvars;
	end else begin
		$dumpfile("dec2_tb.vcd");
		$dumpvars;
	end
end
endmodule

1.combination/dec2/vcd/dec2.vcd
$date
	Thu Jun 27 20:42:55 2024
$end
$version
	Icarus Verilog
$end
$timescale
	1s
$end
$scope module dec2_tb $end
$var wire 4 ! o_out_f [3:0] $end
$var wire 4 " o_out_b [3:0] $end
$var reg 1 # i_en $end
$var reg 2 $ i_in [1:0] $end
$var reg 256 % vcd_file [255:0] $end
$var integer 32 & i [31:0] $end
$scope module u_dec2_behavior $end
$var wire 1 # i_en $end
$var wire 2 ' i_in [1:0] $end
$var reg 4 ( o_out [3:0] $end
$upscope $end
$scope module u_dec2_dataflow $end
$var wire 1 # i_en $end
$var wire 2 ) i_in [1:0] $end
$var wire 4 * o_out [3:0] $end
$upscope $end
$scope task init $end
$upscope $end
$upscope $end
$enddefinitions $end
#0
$dumpvars
b0 *
b10 )
b0 (
b10 '
b0 &
b10111000101111011101100110001101100100001011110110010001100101011000110011001000101110011101100110001101100100 %
b10 $
0#
b0 "
b0 !
$end
#10
b1 $
b1 '
b1 )
b1 &
#20
b0 $
b0 '
b0 )
b10 &
#30
b1 !
b1 *
b1 "
b1 (
1#
b11 &
#40
b0 !
b0 *
b0 "
b0 (
b10 $
b10 '
b10 )
0#
b100 &
#50
b11 $
b11 '
b11 )
b101 &
#60
b1 !
b1 *
b1 "
b1 (
b0 $
b0 '
b0 )
1#
b110 &
#70
b0 !
b0 *
b0 "
b0 (
0#
b111 &
#80
b10 $
b10 '
b10 )
b1000 &
#90
b1001 &
#100
b100 !
b100 *
b100 "
b100 (
1#
b1010 &
#110
b0 !
b0 *
b0 "
b0 (
0#
b1011 &
#120
b1000 !
b1000 *
b1000 "
b1000 (
b11 $
b11 '
b11 )
1#
b1100 &
#130
b0 !
b0 *
b0 "
b0 (
0#
b1101 &
#140
b1000 !
b1000 *
b1000 "
b1000 (
1#
b1110 &
#150
b10 "
b10 (
b10 !
b10 *
b1 $
b1 '
b1 )
b1111 &
#160
b10000 &
#170
b0 !
b0 *
b0 "
b0 (
0#
b10001 &
#180
b1000 !
b1000 *
b1000 "
b1000 (
b11 $
b11 '
b11 )
1#
b10010 &
#190
b1 "
b1 (
b1 !
b1 *
b0 $
b0 '
b0 )
b10011 &
#200
b10100 &
