project_0/02_alu/alu.v
module alu
#(
	parameter	BIT		= 32
)
(
	output reg	[31:0]	o_data_y,
	output 				o_data_c,
	input		[31:0]	i_data_a,
	input		[31:0]	i_data_b,
	input		[2:0]	i_func
);
	wire 	 	[31:0]	data_b_n;
	wire 	 	[31:0]	data_sum;
	

	assign	data_b_n	= (i_func[2] == 1) ? ~i_data_b : i_data_b;

	assign	{o_data_c, data_sum}	= i_data_a + data_b_n;

	always @(*) begin
		case (i_func[1:0])
			2'b00	: o_data_y	= i_data_a & data_b_n;
			2'b01	: o_data_y	= i_data_a | data_b_n;
			2'b10	: o_data_y	= data_sum;
			default	: o_data_y	= i_func[2] ? i_data_a < i_data_b : 'd0;
		endcase
	end

endmodule

project_0/02_alu/alu_tb.v
`define CLKFREQ		100
`define SIMCYCLE	10
`define BIT			32

`include "alu.v"

module alu_tb;

// ==================================================================
// DUT Signals & Instantiation
// ==================================================================
	wire	[`BIT-1:0]		o_data_y;
	wire					o_data_c;
	reg		[`BIT-1:0]		i_data_a;
	reg		[`BIT-1:0]		i_data_b;
	reg		[2:0]			i_func;
	reg						i_clk;

	alu
	#(
		.BIT		(`BIT)
	)
	u_alu
	(
		.o_data_y	(o_data_y	),
		.o_data_c	(o_data_c	),
		.i_data_a	(i_data_a	),
		.i_data_b	(i_data_b	),
		.i_func		(i_func		)
	);	


// ==================================================================
// Clock
// ==================================================================
	always	#(1000/`CLKFREQ)		i_clk = ~i_clk;

// ==================================================================
// Task
// ==================================================================
	task init;
		begin
		i_data_a	= 0;
		i_data_b	= 0;
		i_func		= 0;
		i_clk		= 0;
		end
	endtask

	integer i;
	task test;
		input	[31:0] data_a;
		input	[31:0] data_b;
		begin
			for(i=0; i<8; i++) begin
			#1;
			i_data_a	=  data_a;
			i_data_b	=  data_b;
			i_func		=  i_func + 1'b1;
			repeat(1) @(posedge i_clk);
			end
		end
	endtask

// ==================================================================
// Test Stimulus
// ==================================================================
	integer j;
	initial begin
		init();
		repeat(2) @(posedge i_clk);
		
		test(32'h5555_5555, 32'h1111_1111);
		test(32'hffff_ffff, 32'hffff_ffff);
		test(32'h1111_1111, 32'haaaa_aaaa);
		for(j=0; j<`SIMCYCLE; j++) begin
			test($random, $random);
		end


		repeat(2) @(posedge i_clk);
		$finish;
		
	end

// ==================================================================
// Dump VCD
// ==================================================================
	reg [8*32-1:0] vcd_file;
	initial begin
		if($value$plusargs("vcd_file=%s", vcd_file)) begin
			$dumpfile(vcd_file);
			$dumpvars;
		end else begin
			$dumpfile("alu.vcd");
			$dumpvars;
		end
	end

endmodule

project_0/02_alu/vcd/alu.vcd
$date
	Mon Jul  8 18:59:07 2024
$end
$version
	Icarus Verilog
$end
$timescale
	1s
$end
$scope module alu_tb $end
$var wire 32 ! o_data_y [31:0] $end
$var wire 1 " o_data_c $end
$var reg 1 # i_clk $end
$var reg 32 $ i_data_a [31:0] $end
$var reg 32 % i_data_b [31:0] $end
$var reg 3 & i_func [2:0] $end
$var reg 256 ' vcd_file [255:0] $end
$var integer 32 ( i [31:0] $end
$var integer 32 ) j [31:0] $end
$scope module u_alu $end
$var wire 32 * i_data_a [31:0] $end
$var wire 32 + i_data_b [31:0] $end
$var wire 3 , i_func [2:0] $end
$var wire 1 " o_data_c $end
$var wire 32 - data_sum [31:0] $end
$var wire 32 . data_b_n [31:0] $end
$var reg 32 / o_data_y [31:0] $end
$upscope $end
$scope task init $end
$upscope $end
$scope task test $end
$var reg 32 0 data_a [31:0] $end
$var reg 32 1 data_b [31:0] $end
$upscope $end
$upscope $end
$enddefinitions $end
#0
$dumpvars
bx 1
bx 0
b0 /
b0 .
b0 -
b0 ,
b0 +
b0 *
bx )
bx (
b101110001011110111011001100011011001000010111101100001011011000111010100101110011101100110001101100100 '
b0 &
b0 %
b0 $
0#
0"
b0 !
$end
#10
1#
#20
0#
#30
b0 (
b10001000100010001000100010001 1
b1010101010101010101010101010101 0
1#
#31
b10001000100010001000100010001 .
b1010101010101010101010101010101 !
b1010101010101010101010101010101 /
b1100110011001100110011001100110 -
b1 &
b1 ,
b10001000100010001000100010001 %
b10001000100010001000100010001 +
b1010101010101010101010101010101 $
b1010101010101010101010101010101 *
#40
0#
#50
b1 (
1#
#51
b1100110011001100110011001100110 !
b1100110011001100110011001100110 /
b10 &
b10 ,
#60
0#
#70
b10 (
1#
#71
b0 !
b0 /
b11 &
b11 ,
#80
0#
#90
b11 (
1#
#91
b1000100010001000100010001000011 -
1"
b11101110111011101110111011101110 .
b1000100010001000100010001000100 !
b1000100010001000100010001000100 /
b100 &
b100 ,
#100
0#
#110
b100 (
1#
#111
b11111111111111111111111111111111 !
b11111111111111111111111111111111 /
b101 &
b101 ,
#120
0#
#130
b101 (
1#
#131
b1000100010001000100010001000011 !
b1000100010001000100010001000011 /
b110 &
b110 ,
#140
0#
#150
b110 (
1#
#151
b0 !
b0 /
b111 &
b111 ,
#160
0#
#170
b111 (
1#
#171
b1100110011001100110011001100110 -
0"
b10001000100010001000100010001 .
b10001000100010001000100010001 !
b10001000100010001000100010001 /
b0 &
b0 ,
#180
0#
#190
b11111111111111111111111111111111 1
b11111111111111111111111111111111 0
b0 (
1#
#191
b11111111111111111111111111111111 .
b11111111111111111111111111111111 !
b11111111111111111111111111111111 /
b11111111111111111111111111111110 -
1"
b1 &
b1 ,
b11111111111111111111111111111111 %
b11111111111111111111111111111111 +
b11111111111111111111111111111111 $
b11111111111111111111111111111111 *
#200
0#
#210
b1 (
1#
#211
b11111111111111111111111111111110 !
b11111111111111111111111111111110 /
b10 &
b10 ,
#220
0#
#230
b10 (
1#
#231
b0 !
b0 /
b11 &
b11 ,
#240
0#
#250
b11 (
1#
#251
b11111111111111111111111111111111 -
0"
b0 .
b0 !
b0 /
b100 &
b100 ,
#260
0#
#270
b100 (
1#
#271
b11111111111111111111111111111111 !
b11111111111111111111111111111111 /
b101 &
b101 ,
#280
0#
#290
b101 (
1#
#291
b110 &
b110 ,
#300
0#
#310
b110 (
1#
#311
b0 !
b0 /
b111 &
b111 ,
#320
0#
#330
b111 (
1#
#331
b11111111111111111111111111111110 -
1"
b11111111111111111111111111111111 !
b11111111111111111111111111111111 /
b11111111111111111111111111111111 .
b0 &
b0 ,
#340
0#
#350
b10101010101010101010101010101010 1
b10001000100010001000100010001 0
b0 (
1#
#351
0"
b10111011101110111011101110111011 !
b10111011101110111011101110111011 /
b10101010101010101010101010101010 .
b10111011101110111011101110111011 -
b1 &
b1 ,
b10101010101010101010101010101010 %
b10101010101010101010101010101010 +
b10001000100010001000100010001 $
b10001000100010001000100010001 *
#360
0#
#370
b1 (
1#
#371
b10 &
b10 ,
#380
0#
#390
b10 (
1#
#391
b0 !
b0 /
b11 &
b11 ,
#400
0#
#410
b11 (
1#
#411
b1100110011001100110011001100110 -
b10001000100010001000100010001 !
b10001000100010001000100010001 /
b1010101010101010101010101010101 .
b100 &
b100 ,
#420
0#
#430
b100 (
1#
#431
b1010101010101010101010101010101 !
b1010101010101010101010101010101 /
b101 &
b101 ,
#440
0#
#450
b101 (
1#
#451
b1100110011001100110011001100110 !
b1100110011001100110011001100110 /
b110 &
b110 ,
#460
0#
#470
b110 (
1#
#471
b1 !
b1 /
b111 &
b111 ,
#480
0#
#490
b111 (
1#
#491
b10111011101110111011101110111011 -
b10101010101010101010101010101010 .
b0 !
b0 /
b0 &
b0 ,
#500
0#
#510
b11000000100010010101111010000001 1
b10010000101010011010100100100 0
b0 )
b0 (
1#
#511
b11000000100010010101111010000001 .
b11010010100111010111111110100101 !
b11010010100111010111111110100101 /
b11010010100111101001001110100101 -
b1 &
b1 ,
b11000000100010010101111010000001 %
b11000000100010010101111010000001 +
b10010000101010011010100100100 $
b10010000101010011010100100100 *
#520
0#
#530
b1 (
1#
#531
b11010010100111101001001110100101 !
b11010010100111101001001110100101 /
b10 &
b10 ,
#540
0#
#550
b10 (
1#
#551
b0 !
b0 /
b11 &
b11 ,
#560
0#
#570
b11 (
1#
#571
b1010001100010111101011010100010 -
b111111011101101010000101111110 .
b10010000101000010000100100100 !
b10010000101000010000100100100 /
b100 &
b100 ,
#580
0#
#590
b100 (
1#
#591
b111111011101111011010101111110 !
b111111011101111011010101111110 /
b101 &
b101 ,
#600
0#
#610
b101 (
1#
#611
b1010001100010111101011010100010 !
b1010001100010111101011010100010 /
b110 &
b110 ,
#620
0#
#630
b110 (
1#
#631
b1 !
b1 /
b111 &
b111 ,
#640
0#
#650
b111 (
1#
#651
b11010010100111101001001110100101 -
b11000000100010010101111010000001 .
b10001010000000000 !
b10001010000000000 /
b0 &
b0 ,
#660
0#
#670
b10110001111100000101011001100011 1
b10000100100001001101011000001001 0
b1 )
b0 (
1#
#671
b10110001111100000101011001100011 .
b10110101111101001101011001101011 !
b10110101111101001101011001101011 /
b110110011101010010110001101100 -
1"
b1 &
b1 ,
b10110001111100000101011001100011 %
b10110001111100000101011001100011 +
b10000100100001001101011000001001 $
b10000100100001001101011000001001 *
#680
0#
#690
b1 (
1#
#691
b110110011101010010110001101100 !
b110110011101010010110001101100 /
b10 &
b10 ,
#700
0#
#710
b10 (
1#
#711
b0 !
b0 /
b11 &
b11 ,
#720
0#
#730
b11 (
1#
#731
b11010010100101000111111110100101 -
0"
b1001110000011111010100110011100 .
b100000001001000000000001000 !
b100000001001000000000001000 /
b100 &
b100 ,
#740
0#
#750
b100 (
1#
#751
b11001110100011111111111110011101 !
b11001110100011111111111110011101 /
b101 &
b101 ,
#760
0#
#770
b101 (
1#
#771
b11010010100101000111111110100101 !
b11010010100101000111111110100101 /
b110 &
b110 ,
#780
0#
#790
b110 (
1#
#791
b1 !
b1 /
b111 &
b111 ,
#800
0#
#810
b111 (
1#
#811
b110110011101010010110001101100 -
1"
b10110001111100000101011001100011 .
b10000000100000000101011000000001 !
b10000000100000000101011000000001 /
b0 &
b0 ,
#820
0#
#830
b1000110110111111001100110001101 1
b110101110010111101100001101 0
b10 )
b0 (
1#
#831
b1000110110111111001100110001101 .
b1000110111111111111101110001101 !
b1000110111111111111101110001101 /
b1001101100110010001010010011010 -
0"
b1 &
b1 ,
b1000110110111111001100110001101 %
b1000110110111111001100110001101 +
b110101110010111101100001101 $
b110101110010111101100001101 *
#840
0#
#850
b1 (
1#
#851
b1001101100110010001010010011010 !
b1001101100110010001010010011010 /
b10 &
b10 ,
#860
0#
#870
b10 (
1#
#871
b0 !
b0 /
b11 &
b11 ,
#880
0#
#890
b11 (
1#
#891
b10111111110110011110000101111111 -
b10111001001000000110011001110010 .
b1000000110001000000000 !
b1000000110001000000000 /
b100 &
b100 ,
#900
0#
#910
b100 (
1#
#911
b10111111101110010111111101111111 !
b10111111101110010111111101111111 /
b101 &
b101 ,
#920
0#
#930
b101 (
1#
#931
b10111111110110011110000101111111 !
b10111111110110011110000101111111 /
b110 &
b110 ,
#940
0#
#950
b110 (
1#
#951
b1 !
b1 /
b111 &
b111 ,
#960
0#
#970
b111 (
1#
#971
b1001101100110010001010010011010 -
b1000110110111111001100110001101 .
b110100110010001100100001101 !
b110100110010001100100001101 /
b0 &
b0 ,
#980
0#
#990
b10001001001101110101001000010010 1
b10110010110000101000010001100101 0
b11 )
b0 (
1#
#991
1"
b10001001001101110101001000010010 .
b10111011111101111101011001110111 !
b10111011111101111101011001110111 /
b111011111110011101011001110111 -
b1 &
b1 ,
b10001001001101110101001000010010 %
b10001001001101110101001000010010 +
b10110010110000101000010001100101 $
b10110010110000101000010001100101 *
#1000
0#
#1010
b1 (
1#
#1011
b111011111110011101011001110111 !
b111011111110011101011001110111 /
b10 &
b10 ,
#1020
0#
#1030
b10 (
1#
#1031
b0 !
b0 /
b11 &
b11 ,
#1040
0#
#1050
b11 (
1#
#1051
b101001100010110011001001010010 -
b1110110110010001010110111101101 .
b110010110000001000010001100101 !
b110010110000001000010001100101 /
b100 &
b100 ,
#1060
0#
#1070
b100 (
1#
#1071
b11110110110010101010110111101101 !
b11110110110010101010110111101101 /
b101 &
b101 ,
#1080
0#
#1090
b101 (
1#
#1091
b101001100010110011001001010010 !
b101001100010110011001001010010 /
b110 &
b110 ,
#1100
0#
#1110
b110 (
1#
#1111
b0 !
b0 /
b111 &
b111 ,
#1120
0#
#1130
b111 (
1#
#1131
b111011111110011101011001110111 -
b10001001001101110101001000010010 .
b10000000000000100000000000000000 !
b10000000000000100000000000000000 /
b0 &
b0 ,
#1140
0#
#1150
b110110101111100110100001101 1
b111100111110001100000001 0
b100 )
b0 (
1#
#1151
b110110101111100110100001101 .
b110111101111110111100001101 !
b110111101111110111100001101 /
b111110010111011000000001110 -
0"
b1 &
b1 ,
b110110101111100110100001101 %
b110110101111100110100001101 +
b111100111110001100000001 $
b111100111110001100000001 *
#1160
0#
#1170
b1 (
1#
#1171
b111110010111011000000001110 !
b111110010111011000000001110 /
b10 &
b10 ,
#1180
0#
#1190
b10 (
1#
#1191
b0 !
b0 /
b11 &
b11 ,
#1200
0#
#1210
b11 (
1#
#1211
b11111010000111000001010111110011 -
b11111001001010000011001011110010 .
b1000000010001000000000 !
b1000000010001000000000 /
b100 &
b100 ,
#1220
0#
#1230
b100 (
1#
#1231
b11111001111110111111001111110011 !
b11111001111110111111001111110011 /
b101 &
b101 ,
#1240
0#
#1250
b101 (
1#
#1251
b11111010000111000001010111110011 !
b11111010000111000001010111110011 /
b110 &
b110 ,
#1260
0#
#1270
b110 (
1#
#1271
b1 !
b1 /
b111 &
b111 ,
#1280
0#
#1290
b111 (
1#
#1291
b111110010111011000000001110 -
b110110101111100110100001101 .
b110100111100000100000001 !
b110100111100000100000001 /
b0 &
b0 ,
#1300
0#
#1310
b11110100011011100110100111101 1
b111011001000111111000101110110 0
b101 )
b0 (
1#
#1311
b11110100011011100110100111101 .
b111111101011111111110101111111 !
b111111101011111111110101111111 /
b1011001101100011011111010110011 -
b1 &
b1 ,
b11110100011011100110100111101 %
b11110100011011100110100111101 +
b111011001000111111000101110110 $
b111011001000111111000101110110 *
#1320
0#
#1330
b1 (
1#
#1331
b1011001101100011011111010110011 !
b1011001101100011011111010110011 /
b10 &
b10 ,
#1340
0#
#1350
b10 (
1#
#1351
b0 !
b0 /
b11 &
b11 ,
#1360
0#
#1370
b11 (
1#
#1371
b11100100101100010010000111000 -
1"
b11100001011100100011001011000010 .
b100001001000100011000001000010 !
b100001001000100011000001000010 /
b100 &
b100 ,
#1380
0#
#1390
b100 (
1#
#1391
b11111011011100111111001111110110 !
b11111011011100111111001111110110 /
b101 &
b101 ,
#1400
0#
#1410
b101 (
1#
#1411
b11100100101100010010000111000 !
b11100100101100010010000111000 /
b110 &
b110 ,
#1420
0#
#1430
b110 (
1#
#1431
b0 !
b0 /
b111 &
b111 ,
#1440
0#
#1450
b111 (
1#
#1451
b1011001101100011011111010110011 -
0"
b11110100011011100110100111101 .
b11010000000011100000100110100 !
b11010000000011100000100110100 /
b0 &
b0 ,
#1460
0#
#1470
b1000110001011011111011110001100 1
b1110110110101000101011111101101 0
b110 )
b0 (
1#
#1471
b1000110001011011111011110001100 .
b1110110111111011111011111101101 !
b1110110111111011111011111101101 /
b10111101000000100100111101111001 -
b1 &
b1 ,
b1000110001011011111011110001100 %
b1000110001011011111011110001100 +
b1110110110101000101011111101101 $
b1110110110101000101011111101101 *
#1480
0#
#1490
b1 (
1#
#1491
b10111101000000100100111101111001 !
b10111101000000100100111101111001 /
b10 &
b10 ,
#1500
0#
#1510
b10 (
1#
#1511
b0 !
b0 /
b11 &
b11 ,
#1520
0#
#1530
b11 (
1#
#1531
b110000101001100110000001100000 -
1"
b10111001110100100000100001110011 .
b110000110100000000000001100001 !
b110000110100000000000001100001 /
b100 &
b100 ,
#1540
0#
#1550
b100 (
1#
#1551
b11111111110101100101111111111111 !
b11111111110101100101111111111111 /
b101 &
b101 ,
#1560
0#
#1570
b101 (
1#
#1571
b110000101001100110000001100000 !
b110000101001100110000001100000 /
b110 &
b110 ,
#1580
0#
#1590
b110 (
1#
#1591
b0 !
b0 /
b111 &
b111 ,
#1600
0#
#1610
b111 (
1#
#1611
b10111101000000100100111101111001 -
0"
b1000110001011011111011110001100 .
b1000110000001000101011110001100 !
b1000110000001000101011110001100 /
b0 &
b0 ,
#1620
0#
#1630
b11100011001101110010010011000110 1
b1111100111111011110100111111001 0
b111 )
b0 (
1#
#1631
1"
b11100011001101110010010011000110 .
b11111111111111111110110111111111 !
b11111111111111111110110111111111 /
b1100000001101010000111010111111 -
b1 &
b1 ,
b11100011001101110010010011000110 %
b11100011001101110010010011000110 +
b1111100111111011110100111111001 $
b1111100111111011110100111111001 *
#1640
0#
#1650
b1 (
1#
#1651
b1100000001101010000111010111111 !
b1100000001101010000111010111111 /
b10 &
b10 ,
#1660
0#
#1670
b10 (
1#
#1671
b0 !
b0 /
b11 &
b11 ,
#1680
0#
#1690
b11 (
1#
#1691
b10011001110001101100010100110010 -
0"
b11100110010001101101100111001 .
b11100110010001100100100111001 !
b11100110010001100100100111001 /
b100 &
b100 ,
#1700
0#
#1710
b100 (
1#
#1711
b1111100111111011111101111111001 !
b1111100111111011111101111111001 /
b101 &
b101 ,
#1720
0#
#1730
b101 (
1#
#1731
b10011001110001101100010100110010 !
b10011001110001101100010100110010 /
b110 &
b110 ,
#1740
0#
#1750
b110 (
1#
#1751
b1 !
b1 /
b111 &
b111 ,
#1760
0#
#1770
b111 (
1#
#1771
b1100000001101010000111010111111 -
1"
b11100011001101110010010011000110 .
b1100000001101010010000011000000 !
b1100000001101010010000011000000 /
b0 &
b0 ,
#1780
0#
#1790
b11010101000100111101001010101010 1
b11100010111101111000010011000101 0
b1000 )
b0 (
1#
#1791
b11010101000100111101001010101010 .
b11110111111101111101011011101111 !
b11110111111101111101011011101111 /
b10111000000010110101011101101111 -
b1 &
b1 ,
b11010101000100111101001010101010 %
b11010101000100111101001010101010 +
b11100010111101111000010011000101 $
b11100010111101111000010011000101 *
#1800
0#
#1810
b1 (
1#
#1811
b10111000000010110101011101101111 !
b10111000000010110101011101101111 /
b10 &
b10 ,
#1820
0#
#1830
b10 (
1#
#1831
b0 !
b0 /
b11 &
b11 ,
#1840
0#
#1850
b11 (
1#
#1851
b1101111000111011001000011010 -
b101010111011000010110101010101 .
b100010111001000000010001000101 !
b100010111001000000010001000101 /
b100 &
b100 ,
#1860
0#
#1870
b100 (
1#
#1871
b11101010111111111010110111010101 !
b11101010111111111010110111010101 /
b101 &
b101 ,
#1880
0#
#1890
b101 (
1#
#1891
b1101111000111011001000011010 !
b1101111000111011001000011010 /
b110 &
b110 ,
#1900
0#
#1910
b110 (
1#
#1911
b0 !
b0 /
b111 &
b111 ,
#1920
0#
#1930
b111 (
1#
#1931
b10111000000010110101011101101111 -
b11010101000100111101001010101010 .
b11000000000100111000000010000000 !
b11000000000100111000000010000000 /
b0 &
b0 ,
#1940
0#
#1950
b10111011110100100111001001110111 1
b1110010101011111111011111100101 0
b1001 )
b0 (
1#
#1951
b10111011110100100111001001110111 .
b11111011111111111111011111110111 !
b11111011111111111111011111110111 /
b101110100000100110101001011100 -
b1 &
b1 ,
b10111011110100100111001001110111 %
b10111011110100100111001001110111 +
b1110010101011111111011111100101 $
b1110010101011111111011111100101 *
#1960
0#
#1970
b1 (
1#
#1971
b101110100000100110101001011100 !
b101110100000100110101001011100 /
b10 &
b10 ,
#1980
0#
#1990
b10 (
1#
#1991
b0 !
b0 /
b11 &
b11 ,
#2000
0#
#2010
b11 (
1#
#2011
b10110110110111011000010101101101 -
0"
b1000100001011011000110110001000 .
b1000000001011011000010110000000 !
b1000000001011011000010110000000 /
b100 &
b100 ,
#2020
0#
#2030
b100 (
1#
#2031
b1110110101011111111111111101101 !
b1110110101011111111111111101101 /
b101 &
b101 ,
#2040
0#
#2050
b101 (
1#
#2051
b10110110110111011000010101101101 !
b10110110110111011000010101101101 /
b110 &
b110 ,
#2060
0#
#2070
b110 (
1#
#2071
b1 !
b1 /
b111 &
b111 ,
#2080
0#
#2090
b111 (
1#
#2091
b101110100000100110101001011100 -
1"
b10111011110100100111001001110111 .
b110010100000100111001001100101 !
b110010100000100111001001100101 /
b0 &
b0 ,
#2100
0#
#2110
b1010 )
b1000 (
1#
