project_0/00_gray_code_converter/gray_code_converter.v
module bin_to_gray
#(
	parameter 	BIT	= 8
)
(
	output 	[BIT-1:0]	o_gray,
	input	[BIT-1:0]	i_bin
);

	`ifdef GENER_TO_GRAY
		genvar	g;
		generate
			for (g=0; g<BIT-1; g=g+1) begin
					assign	o_gray[g]	= i_bin[g+1] ^ i_bin[g]; 
			end
		endgenerate
		assign	o_gray[BIT-1]	= i_bin[BIT-1]; 			// MSB

	`else
		assign	o_gray[0]		= i_bin[1] ^ i_bin[0];
		assign	o_gray[1]		= i_bin[2] ^ i_bin[1];
		assign	o_gray[2]		= i_bin[3] ^ i_bin[2];
		assign	o_gray[3]		= i_bin[4] ^ i_bin[3];
		assign	o_gray[4]		= i_bin[5] ^ i_bin[4];
		assign	o_gray[5]		= i_bin[6] ^ i_bin[5];
		assign	o_gray[6]		= i_bin[7] ^ i_bin[6];
		assign	o_gray[7]		= i_bin[7]; 					// MSB
	`endif

endmodule

module gray_to_bin
#(
	parameter 	BIT	= 8
)
(
	output	[BIT-1:0]	o_bin,
	input	[BIT-1:0]	i_gray
);

	`ifdef GENER_TO_BIN
		genvar	g;
		generate
			for (g=0; g<BIT-1; g=g+1) begin
					assign	o_bin[g]	= o_bin[g+1] ^ i_gray[g]; 
			end
		endgenerate
		assign	o_bin[BIT-1]	= i_gray[BIT-1]; 			// MSB

	`else
		assign	o_bin[0]		= o_bin[1] ^ i_gray[0];
		assign	o_bin[1]		= o_bin[2] ^ i_gray[1];
		assign	o_bin[2]		= o_bin[3] ^ i_gray[2];
		assign	o_bin[3]		= o_bin[4] ^ i_gray[3];
		assign	o_bin[4]		= o_bin[5] ^ i_gray[4];
		assign	o_bin[5]		= o_bin[6] ^ i_gray[5];
		assign	o_bin[6]		= o_bin[7] ^ i_gray[6];
		assign	o_bin[7]		= i_gray[7]; 					// MSB
	`endif

endmodule

project_0/00_gray_code_converter/gray_code_converter_tb.v
`define CLKFREQ		100
`define SIMCYCLE	256
`define BIT			8

`define GENER_TO_GRAY
`define GENER_TO_BIN

`include "gray_code_converter.v"

module gray_code_converter_tb;
	
	wire	[`BIT-1:0]	o_gray;
	wire	[`BIT-1:0]	o_bin;
	reg		[`BIT-1:0]	i_bin;
	reg					i_clk;
	reg					i_rstn;

	bin_to_gray
	#(
		.BIT		(`BIT)
	)
	u_bin_to_gray(
		.o_gray		(o_gray),
		.i_bin		(i_bin)
	);

	gray_to_bin
	#(
		.BIT		(`BIT)
	)
	u_gray_to_bin(
		.o_bin		(o_bin),
		.i_gray		(o_gray)
	);

	always	#(500/`CLKFREQ)		i_clk = ~i_clk;


	task init;
		begin
			i_bin	=	0;
			i_clk	=	0;
			i_rstn	=	0; 
			@(posedge i_clk);
		end
	endtask


	integer	i;
	initial begin
		init();
		
		for (i=0; i<`SIMCYCLE; i++) begin
			i_bin	= i_bin + 8'b1;
			@(posedge i_clk);
		end

		$finish;
	end

	reg [8*32-1:0] vcd_file;
	initial begin
		if($value$plusargs("vcd_file=%s", vcd_file)) begin
			$dumpfile(vcd_file);
			$dumpvars;
		end else begin
			$dumpfile("gray_code_converter.vcd");
			$dumpvars;
		end
	end

endmodule

project_0/00_gray_code_converter/vcd/gray_code_converter.vcd
$date
	Sat Jul  6 20:06:37 2024
$end
$version
	Icarus Verilog
$end
$timescale
	1s
$end
$scope module gray_code_converter_tb $end
$var wire 8 ! o_gray [7:0] $end
$var wire 8 " o_bin [7:0] $end
$var reg 8 # i_bin [7:0] $end
$var reg 1 $ i_clk $end
$var reg 1 % i_rstn $end
$var reg 256 & vcd_file [255:0] $end
$var integer 32 ' i [31:0] $end
$scope module u_bin_to_gray $end
$var wire 8 ( i_bin [7:0] $end
$var wire 8 ) o_gray [7:0] $end
$scope begin genblk1[0] $end
$upscope $end
$scope begin genblk1[1] $end
$upscope $end
$scope begin genblk1[2] $end
$upscope $end
$scope begin genblk1[3] $end
$upscope $end
$scope begin genblk1[4] $end
$upscope $end
$scope begin genblk1[5] $end
$upscope $end
$scope begin genblk1[6] $end
$upscope $end
$upscope $end
$scope module u_gray_to_bin $end
$var wire 8 * i_gray [7:0] $end
$var wire 8 + o_bin [7:0] $end
$scope begin genblk1[0] $end
$upscope $end
$scope begin genblk1[1] $end
$upscope $end
$scope begin genblk1[2] $end
$upscope $end
$scope begin genblk1[3] $end
$upscope $end
$scope begin genblk1[4] $end
$upscope $end
$scope begin genblk1[5] $end
$upscope $end
$scope begin genblk1[6] $end
$upscope $end
$upscope $end
$scope task init $end
$upscope $end
$upscope $end
$enddefinitions $end
#0
$dumpvars
b0 +
b0 *
b0 )
b0 (
bx '
b10111000101111011101100110001101100100001011110110011101110010011000010111100101011111011000110110111101100100011001010101111101100011011011110110111001110110011001010111001001110100011001010111001000101110011101100110001101100100 &
0%
0$
b0 #
b0 "
b0 !
$end
#5
b1 "
b1 +
b1 !
b1 )
b1 *
b1 #
b1 (
b0 '
1$
#10
0$
#15
b10 "
b10 +
b11 !
b11 )
b11 *
b10 #
b10 (
b1 '
1$
#20
0$
#25
b11 "
b11 +
b10 !
b10 )
b10 *
b11 #
b11 (
b10 '
1$
#30
0$
#35
b100 "
b100 +
b110 !
b110 )
b110 *
b100 #
b100 (
b11 '
1$
#40
0$
#45
b101 "
b101 +
b111 !
b111 )
b111 *
b101 #
b101 (
b100 '
1$
#50
0$
#55
b110 "
b110 +
b101 !
b101 )
b101 *
b110 #
b110 (
b101 '
1$
#60
0$
#65
b111 "
b111 +
b100 !
b100 )
b100 *
b111 #
b111 (
b110 '
1$
#70
0$
#75
b1000 "
b1000 +
b1100 !
b1100 )
b1100 *
b1000 #
b1000 (
b111 '
1$
#80
0$
#85
b1001 "
b1001 +
b1101 !
b1101 )
b1101 *
b1001 #
b1001 (
b1000 '
1$
#90
0$
#95
b1010 "
b1010 +
b1111 !
b1111 )
b1111 *
b1010 #
b1010 (
b1001 '
1$
#100
0$
#105
b1011 "
b1011 +
b1110 !
b1110 )
b1110 *
b1011 #
b1011 (
b1010 '
1$
#110
0$
#115
b1100 "
b1100 +
b1010 !
b1010 )
b1010 *
b1100 #
b1100 (
b1011 '
1$
#120
0$
#125
b1101 "
b1101 +
b1011 !
b1011 )
b1011 *
b1101 #
b1101 (
b1100 '
1$
#130
0$
#135
b1110 "
b1110 +
b1001 !
b1001 )
b1001 *
b1110 #
b1110 (
b1101 '
1$
#140
0$
#145
b1111 "
b1111 +
b1000 !
b1000 )
b1000 *
b1111 #
b1111 (
b1110 '
1$
#150
0$
#155
b10000 "
b10000 +
b11000 !
b11000 )
b11000 *
b10000 #
b10000 (
b1111 '
1$
#160
0$
#165
b10001 "
b10001 +
b11001 !
b11001 )
b11001 *
b10001 #
b10001 (
b10000 '
1$
#170
0$
#175
b10010 "
b10010 +
b11011 !
b11011 )
b11011 *
b10010 #
b10010 (
b10001 '
1$
#180
0$
#185
b10011 "
b10011 +
b11010 !
b11010 )
b11010 *
b10011 #
b10011 (
b10010 '
1$
#190
0$
#195
b10100 "
b10100 +
b11110 !
b11110 )
b11110 *
b10100 #
b10100 (
b10011 '
1$
#200
0$
#205
b10101 "
b10101 +
b11111 !
b11111 )
b11111 *
b10101 #
b10101 (
b10100 '
1$
#210
0$
#215
b10110 "
b10110 +
b11101 !
b11101 )
b11101 *
b10110 #
b10110 (
b10101 '
1$
#220
0$
#225
b10111 "
b10111 +
b11100 !
b11100 )
b11100 *
b10111 #
b10111 (
b10110 '
1$
#230
0$
#235
b11000 "
b11000 +
b10100 !
b10100 )
b10100 *
b11000 #
b11000 (
b10111 '
1$
#240
0$
#245
b11001 "
b11001 +
b10101 !
b10101 )
b10101 *
b11001 #
b11001 (
b11000 '
1$
#250
0$
#255
b11010 "
b11010 +
b10111 !
b10111 )
b10111 *
b11010 #
b11010 (
b11001 '
1$
#260
0$
#265
b11011 "
b11011 +
b10110 !
b10110 )
b10110 *
b11011 #
b11011 (
b11010 '
1$
#270
0$
#275
b11100 "
b11100 +
b10010 !
b10010 )
b10010 *
b11100 #
b11100 (
b11011 '
1$
#280
0$
#285
b11101 "
b11101 +
b10011 !
b10011 )
b10011 *
b11101 #
b11101 (
b11100 '
1$
#290
0$
#295
b11110 "
b11110 +
b10001 !
b10001 )
b10001 *
b11110 #
b11110 (
b11101 '
1$
#300
0$
#305
b11111 "
b11111 +
b10000 !
b10000 )
b10000 *
b11111 #
b11111 (
b11110 '
1$
#310
0$
#315
b100000 "
b100000 +
b110000 !
b110000 )
b110000 *
b100000 #
b100000 (
b11111 '
1$
#320
0$
#325
b100001 "
b100001 +
b110001 !
b110001 )
b110001 *
b100001 #
b100001 (
b100000 '
1$
#330
0$
#335
b100010 "
b100010 +
b110011 !
b110011 )
b110011 *
b100010 #
b100010 (
b100001 '
1$
#340
0$
#345
b100011 "
b100011 +
b110010 !
b110010 )
b110010 *
b100011 #
b100011 (
b100010 '
1$
#350
0$
#355
b100100 "
b100100 +
b110110 !
b110110 )
b110110 *
b100100 #
b100100 (
b100011 '
1$
#360
0$
#365
b100101 "
b100101 +
b110111 !
b110111 )
b110111 *
b100101 #
b100101 (
b100100 '
1$
#370
0$
#375
b100110 "
b100110 +
b110101 !
b110101 )
b110101 *
b100110 #
b100110 (
b100101 '
1$
#380
0$
#385
b100111 "
b100111 +
b110100 !
b110100 )
b110100 *
b100111 #
b100111 (
b100110 '
1$
#390
0$
#395
b101000 "
b101000 +
b111100 !
b111100 )
b111100 *
b101000 #
b101000 (
b100111 '
1$
#400
0$
#405
b101001 "
b101001 +
b111101 !
b111101 )
b111101 *
b101001 #
b101001 (
b101000 '
1$
#410
0$
#415
b101010 "
b101010 +
b111111 !
b111111 )
b111111 *
b101010 #
b101010 (
b101001 '
1$
#420
0$
#425
b101011 "
b101011 +
b111110 !
b111110 )
b111110 *
b101011 #
b101011 (
b101010 '
1$
#430
0$
#435
b101100 "
b101100 +
b111010 !
b111010 )
b111010 *
b101100 #
b101100 (
b101011 '
1$
#440
0$
#445
b101101 "
b101101 +
b111011 !
b111011 )
b111011 *
b101101 #
b101101 (
b101100 '
1$
#450
0$
#455
b101110 "
b101110 +
b111001 !
b111001 )
b111001 *
b101110 #
b101110 (
b101101 '
1$
#460
0$
#465
b101111 "
b101111 +
b111000 !
b111000 )
b111000 *
b101111 #
b101111 (
b101110 '
1$
#470
0$
#475
b110000 "
b110000 +
b101000 !
b101000 )
b101000 *
b110000 #
b110000 (
b101111 '
1$
#480
0$
#485
b110001 "
b110001 +
b101001 !
b101001 )
b101001 *
b110001 #
b110001 (
b110000 '
1$
#490
0$
#495
b110010 "
b110010 +
b101011 !
b101011 )
b101011 *
b110010 #
b110010 (
b110001 '
1$
#500
0$
#505
b110011 "
b110011 +
b101010 !
b101010 )
b101010 *
b110011 #
b110011 (
b110010 '
1$
#510
0$
#515
b110100 "
b110100 +
b101110 !
b101110 )
b101110 *
b110100 #
b110100 (
b110011 '
1$
#520
0$
#525
b110101 "
b110101 +
b101111 !
b101111 )
b101111 *
b110101 #
b110101 (
b110100 '
1$
#530
0$
#535
b110110 "
b110110 +
b101101 !
b101101 )
b101101 *
b110110 #
b110110 (
b110101 '
1$
#540
0$
#545
b110111 "
b110111 +
b101100 !
b101100 )
b101100 *
b110111 #
b110111 (
b110110 '
1$
#550
0$
#555
b111000 "
b111000 +
b100100 !
b100100 )
b100100 *
b111000 #
b111000 (
b110111 '
1$
#560
0$
#565
b111001 "
b111001 +
b100101 !
b100101 )
b100101 *
b111001 #
b111001 (
b111000 '
1$
#570
0$
#575
b111010 "
b111010 +
b100111 !
b100111 )
b100111 *
b111010 #
b111010 (
b111001 '
1$
#580
0$
#585
b111011 "
b111011 +
b100110 !
b100110 )
b100110 *
b111011 #
b111011 (
b111010 '
1$
#590
0$
#595
b111100 "
b111100 +
b100010 !
b100010 )
b100010 *
b111100 #
b111100 (
b111011 '
1$
#600
0$
#605
b111101 "
b111101 +
b100011 !
b100011 )
b100011 *
b111101 #
b111101 (
b111100 '
1$
#610
0$
#615
b111110 "
b111110 +
b100001 !
b100001 )
b100001 *
b111110 #
b111110 (
b111101 '
1$
#620
0$
#625
b111111 "
b111111 +
b100000 !
b100000 )
b100000 *
b111111 #
b111111 (
b111110 '
1$
#630
0$
#635
b1000000 "
b1000000 +
b1100000 !
b1100000 )
b1100000 *
b1000000 #
b1000000 (
b111111 '
1$
#640
0$
#645
b1000001 "
b1000001 +
b1100001 !
b1100001 )
b1100001 *
b1000001 #
b1000001 (
b1000000 '
1$
#650
0$
#655
b1000010 "
b1000010 +
b1100011 !
b1100011 )
b1100011 *
b1000010 #
b1000010 (
b1000001 '
1$
#660
0$
#665
b1000011 "
b1000011 +
b1100010 !
b1100010 )
b1100010 *
b1000011 #
b1000011 (
b1000010 '
1$
#670
0$
#675
b1000100 "
b1000100 +
b1100110 !
b1100110 )
b1100110 *
b1000100 #
b1000100 (
b1000011 '
1$
#680
0$
#685
b1000101 "
b1000101 +
b1100111 !
b1100111 )
b1100111 *
b1000101 #
b1000101 (
b1000100 '
1$
#690
0$
#695
b1000110 "
b1000110 +
b1100101 !
b1100101 )
b1100101 *
b1000110 #
b1000110 (
b1000101 '
1$
#700
0$
#705
b1000111 "
b1000111 +
b1100100 !
b1100100 )
b1100100 *
b1000111 #
b1000111 (
b1000110 '
1$
#710
0$
#715
b1001000 "
b1001000 +
b1101100 !
b1101100 )
b1101100 *
b1001000 #
b1001000 (
b1000111 '
1$
#720
0$
#725
b1001001 "
b1001001 +
b1101101 !
b1101101 )
b1101101 *
b1001001 #
b1001001 (
b1001000 '
1$
#730
0$
#735
b1001010 "
b1001010 +
b1101111 !
b1101111 )
b1101111 *
b1001010 #
b1001010 (
b1001001 '
1$
#740
0$
#745
b1001011 "
b1001011 +
b1101110 !
b1101110 )
b1101110 *
b1001011 #
b1001011 (
b1001010 '
1$
#750
0$
#755
b1001100 "
b1001100 +
b1101010 !
b1101010 )
b1101010 *
b1001100 #
b1001100 (
b1001011 '
1$
#760
0$
#765
b1001101 "
b1001101 +
b1101011 !
b1101011 )
b1101011 *
b1001101 #
b1001101 (
b1001100 '
1$
#770
0$
#775
b1001110 "
b1001110 +
b1101001 !
b1101001 )
b1101001 *
b1001110 #
b1001110 (
b1001101 '
1$
#780
0$
#785
b1001111 "
b1001111 +
b1101000 !
b1101000 )
b1101000 *
b1001111 #
b1001111 (
b1001110 '
1$
#790
0$
#795
b1010000 "
b1010000 +
b1111000 !
b1111000 )
b1111000 *
b1010000 #
b1010000 (
b1001111 '
1$
#800
0$
#805
b1010001 "
b1010001 +
b1111001 !
b1111001 )
b1111001 *
b1010001 #
b1010001 (
b1010000 '
1$
#810
0$
#815
b1010010 "
b1010010 +
b1111011 !
b1111011 )
b1111011 *
b1010010 #
b1010010 (
b1010001 '
1$
#820
0$
#825
b1010011 "
b1010011 +
b1111010 !
b1111010 )
b1111010 *
b1010011 #
b1010011 (
b1010010 '
1$
#830
0$
#835
b1010100 "
b1010100 +
b1111110 !
b1111110 )
b1111110 *
b1010100 #
b1010100 (
b1010011 '
1$
#840
0$
#845
b1010101 "
b1010101 +
b1111111 !
b1111111 )
b1111111 *
b1010101 #
b1010101 (
b1010100 '
1$
#850
0$
#855
b1010110 "
b1010110 +
b1111101 !
b1111101 )
b1111101 *
b1010110 #
b1010110 (
b1010101 '
1$
#860
0$
#865
b1010111 "
b1010111 +
b1111100 !
b1111100 )
b1111100 *
b1010111 #
b1010111 (
b1010110 '
1$
#870
0$
#875
b1011000 "
b1011000 +
b1110100 !
b1110100 )
b1110100 *
b1011000 #
b1011000 (
b1010111 '
1$
#880
0$
#885
b1011001 "
b1011001 +
b1110101 !
b1110101 )
b1110101 *
b1011001 #
b1011001 (
b1011000 '
1$
#890
0$
#895
b1011010 "
b1011010 +
b1110111 !
b1110111 )
b1110111 *
b1011010 #
b1011010 (
b1011001 '
1$
#900
0$
#905
b1011011 "
b1011011 +
b1110110 !
b1110110 )
b1110110 *
b1011011 #
b1011011 (
b1011010 '
1$
#910
0$
#915
b1011100 "
b1011100 +
b1110010 !
b1110010 )
b1110010 *
b1011100 #
b1011100 (
b1011011 '
1$
#920
0$
#925
b1011101 "
b1011101 +
b1110011 !
b1110011 )
b1110011 *
b1011101 #
b1011101 (
b1011100 '
1$
#930
0$
#935
b1011110 "
b1011110 +
b1110001 !
b1110001 )
b1110001 *
b1011110 #
b1011110 (
b1011101 '
1$
#940
0$
#945
b1011111 "
b1011111 +
b1110000 !
b1110000 )
b1110000 *
b1011111 #
b1011111 (
b1011110 '
1$
#950
0$
#955
b1100000 "
b1100000 +
b1010000 !
b1010000 )
b1010000 *
b1100000 #
b1100000 (
b1011111 '
1$
#960
0$
#965
b1100001 "
b1100001 +
b1010001 !
b1010001 )
b1010001 *
b1100001 #
b1100001 (
b1100000 '
1$
#970
0$
#975
b1100010 "
b1100010 +
b1010011 !
b1010011 )
b1010011 *
b1100010 #
b1100010 (
b1100001 '
1$
#980
0$
#985
b1100011 "
b1100011 +
b1010010 !
b1010010 )
b1010010 *
b1100011 #
b1100011 (
b1100010 '
1$
#990
0$
#995
b1100100 "
b1100100 +
b1010110 !
b1010110 )
b1010110 *
b1100100 #
b1100100 (
b1100011 '
1$
#1000
0$
#1005
b1100101 "
b1100101 +
b1010111 !
b1010111 )
b1010111 *
b1100101 #
b1100101 (
b1100100 '
1$
#1010
0$
#1015
b1100110 "
b1100110 +
b1010101 !
b1010101 )
b1010101 *
b1100110 #
b1100110 (
b1100101 '
1$
#1020
0$
#1025
b1100111 "
b1100111 +
b1010100 !
b1010100 )
b1010100 *
b1100111 #
b1100111 (
b1100110 '
1$
#1030
0$
#1035
b1101000 "
b1101000 +
b1011100 !
b1011100 )
b1011100 *
b1101000 #
b1101000 (
b1100111 '
1$
#1040
0$
#1045
b1101001 "
b1101001 +
b1011101 !
b1011101 )
b1011101 *
b1101001 #
b1101001 (
b1101000 '
1$
#1050
0$
#1055
b1101010 "
b1101010 +
b1011111 !
b1011111 )
b1011111 *
b1101010 #
b1101010 (
b1101001 '
1$
#1060
0$
#1065
b1101011 "
b1101011 +
b1011110 !
b1011110 )
b1011110 *
b1101011 #
b1101011 (
b1101010 '
1$
#1070
0$
#1075
b1101100 "
b1101100 +
b1011010 !
b1011010 )
b1011010 *
b1101100 #
b1101100 (
b1101011 '
1$
#1080
0$
#1085
b1101101 "
b1101101 +
b1011011 !
b1011011 )
b1011011 *
b1101101 #
b1101101 (
b1101100 '
1$
#1090
0$
#1095
b1101110 "
b1101110 +
b1011001 !
b1011001 )
b1011001 *
b1101110 #
b1101110 (
b1101101 '
1$
#1100
0$
#1105
b1101111 "
b1101111 +
b1011000 !
b1011000 )
b1011000 *
b1101111 #
b1101111 (
b1101110 '
1$
#1110
0$
#1115
b1110000 "
b1110000 +
b1001000 !
b1001000 )
b1001000 *
b1110000 #
b1110000 (
b1101111 '
1$
#1120
0$
#1125
b1110001 "
b1110001 +
b1001001 !
b1001001 )
b1001001 *
b1110001 #
b1110001 (
b1110000 '
1$
#1130
0$
#1135
b1110010 "
b1110010 +
b1001011 !
b1001011 )
b1001011 *
b1110010 #
b1110010 (
b1110001 '
1$
#1140
0$
#1145
b1110011 "
b1110011 +
b1001010 !
b1001010 )
b1001010 *
b1110011 #
b1110011 (
b1110010 '
1$
#1150
0$
#1155
b1110100 "
b1110100 +
b1001110 !
b1001110 )
b1001110 *
b1110100 #
b1110100 (
b1110011 '
1$
#1160
0$
#1165
b1110101 "
b1110101 +
b1001111 !
b1001111 )
b1001111 *
b1110101 #
b1110101 (
b1110100 '
1$
#1170
0$
#1175
b1110110 "
b1110110 +
b1001101 !
b1001101 )
b1001101 *
b1110110 #
b1110110 (
b1110101 '
1$
#1180
0$
#1185
b1110111 "
b1110111 +
b1001100 !
b1001100 )
b1001100 *
b1110111 #
b1110111 (
b1110110 '
1$
#1190
0$
#1195
b1111000 "
b1111000 +
b1000100 !
b1000100 )
b1000100 *
b1111000 #
b1111000 (
b1110111 '
1$
#1200
0$
#1205
b1111001 "
b1111001 +
b1000101 !
b1000101 )
b1000101 *
b1111001 #
b1111001 (
b1111000 '
1$
#1210
0$
#1215
b1111010 "
b1111010 +
b1000111 !
b1000111 )
b1000111 *
b1111010 #
b1111010 (
b1111001 '
1$
#1220
0$
#1225
b1111011 "
b1111011 +
b1000110 !
b1000110 )
b1000110 *
b1111011 #
b1111011 (
b1111010 '
1$
#1230
0$
#1235
b1111100 "
b1111100 +
b1000010 !
b1000010 )
b1000010 *
b1111100 #
b1111100 (
b1111011 '
1$
#1240
0$
#1245
b1111101 "
b1111101 +
b1000011 !
b1000011 )
b1000011 *
b1111101 #
b1111101 (
b1111100 '
1$
#1250
0$
#1255
b1111110 "
b1111110 +
b1000001 !
b1000001 )
b1000001 *
b1111110 #
b1111110 (
b1111101 '
1$
#1260
0$
#1265
b1111111 "
b1111111 +
b1000000 !
b1000000 )
b1000000 *
b1111111 #
b1111111 (
b1111110 '
1$
#1270
0$
#1275
b10000000 "
b10000000 +
b11000000 !
b11000000 )
b11000000 *
b10000000 #
b10000000 (
b1111111 '
1$
#1280
0$
#1285
b10000001 "
b10000001 +
b11000001 !
b11000001 )
b11000001 *
b10000001 #
b10000001 (
b10000000 '
1$
#1290
0$
#1295
b10000010 "
b10000010 +
b11000011 !
b11000011 )
b11000011 *
b10000010 #
b10000010 (
b10000001 '
1$
#1300
0$
#1305
b10000011 "
b10000011 +
b11000010 !
b11000010 )
b11000010 *
b10000011 #
b10000011 (
b10000010 '
1$
#1310
0$
#1315
b10000100 "
b10000100 +
b11000110 !
b11000110 )
b11000110 *
b10000100 #
b10000100 (
b10000011 '
1$
#1320
0$
#1325
b10000101 "
b10000101 +
b11000111 !
b11000111 )
b11000111 *
b10000101 #
b10000101 (
b10000100 '
1$
#1330
0$
#1335
b10000110 "
b10000110 +
b11000101 !
b11000101 )
b11000101 *
b10000110 #
b10000110 (
b10000101 '
1$
#1340
0$
#1345
b10000111 "
b10000111 +
b11000100 !
b11000100 )
b11000100 *
b10000111 #
b10000111 (
b10000110 '
1$
#1350
0$
#1355
b10001000 "
b10001000 +
b11001100 !
b11001100 )
b11001100 *
b10001000 #
b10001000 (
b10000111 '
1$
#1360
0$
#1365
b10001001 "
b10001001 +
b11001101 !
b11001101 )
b11001101 *
b10001001 #
b10001001 (
b10001000 '
1$
#1370
0$
#1375
b10001010 "
b10001010 +
b11001111 !
b11001111 )
b11001111 *
b10001010 #
b10001010 (
b10001001 '
1$
#1380
0$
#1385
b10001011 "
b10001011 +
b11001110 !
b11001110 )
b11001110 *
b10001011 #
b10001011 (
b10001010 '
1$
#1390
0$
#1395
b10001100 "
b10001100 +
b11001010 !
b11001010 )
b11001010 *
b10001100 #
b10001100 (
b10001011 '
1$
#1400
0$
#1405
b10001101 "
b10001101 +
b11001011 !
b11001011 )
b11001011 *
b10001101 #
b10001101 (
b10001100 '
1$
#1410
0$
#1415
b10001110 "
b10001110 +
b11001001 !
b11001001 )
b11001001 *
b10001110 #
b10001110 (
b10001101 '
1$
#1420
0$
#1425
b10001111 "
b10001111 +
b11001000 !
b11001000 )
b11001000 *
b10001111 #
b10001111 (
b10001110 '
1$
#1430
0$
#1435
b10010000 "
b10010000 +
b11011000 !
b11011000 )
b11011000 *
b10010000 #
b10010000 (
b10001111 '
1$
#1440
0$
#1445
b10010001 "
b10010001 +
b11011001 !
b11011001 )
b11011001 *
b10010001 #
b10010001 (
b10010000 '
1$
#1450
0$
#1455
b10010010 "
b10010010 +
b11011011 !
b11011011 )
b11011011 *
b10010010 #
b10010010 (
b10010001 '
1$
#1460
0$
#1465
b10010011 "
b10010011 +
b11011010 !
b11011010 )
b11011010 *
b10010011 #
b10010011 (
b10010010 '
1$
#1470
0$
#1475
b10010100 "
b10010100 +
b11011110 !
b11011110 )
b11011110 *
b10010100 #
b10010100 (
b10010011 '
1$
#1480
0$
#1485
b10010101 "
b10010101 +
b11011111 !
b11011111 )
b11011111 *
b10010101 #
b10010101 (
b10010100 '
1$
#1490
0$
#1495
b10010110 "
b10010110 +
b11011101 !
b11011101 )
b11011101 *
b10010110 #
b10010110 (
b10010101 '
1$
#1500
0$
#1505
b10010111 "
b10010111 +
b11011100 !
b11011100 )
b11011100 *
b10010111 #
b10010111 (
b10010110 '
1$
#1510
0$
#1515
b10011000 "
b10011000 +
b11010100 !
b11010100 )
b11010100 *
b10011000 #
b10011000 (
b10010111 '
1$
#1520
0$
#1525
b10011001 "
b10011001 +
b11010101 !
b11010101 )
b11010101 *
b10011001 #
b10011001 (
b10011000 '
1$
#1530
0$
#1535
b10011010 "
b10011010 +
b11010111 !
b11010111 )
b11010111 *
b10011010 #
b10011010 (
b10011001 '
1$
#1540
0$
#1545
b10011011 "
b10011011 +
b11010110 !
b11010110 )
b11010110 *
b10011011 #
b10011011 (
b10011010 '
1$
#1550
0$
#1555
b10011100 "
b10011100 +
b11010010 !
b11010010 )
b11010010 *
b10011100 #
b10011100 (
b10011011 '
1$
#1560
0$
#1565
b10011101 "
b10011101 +
b11010011 !
b11010011 )
b11010011 *
b10011101 #
b10011101 (
b10011100 '
1$
#1570
0$
#1575
b10011110 "
b10011110 +
b11010001 !
b11010001 )
b11010001 *
b10011110 #
b10011110 (
b10011101 '
1$
#1580
0$
#1585
b10011111 "
b10011111 +
b11010000 !
b11010000 )
b11010000 *
b10011111 #
b10011111 (
b10011110 '
1$
#1590
0$
#1595
b10100000 "
b10100000 +
b11110000 !
b11110000 )
b11110000 *
b10100000 #
b10100000 (
b10011111 '
1$
#1600
0$
#1605
b10100001 "
b10100001 +
b11110001 !
b11110001 )
b11110001 *
b10100001 #
b10100001 (
b10100000 '
1$
#1610
0$
#1615
b10100010 "
b10100010 +
b11110011 !
b11110011 )
b11110011 *
b10100010 #
b10100010 (
b10100001 '
1$
#1620
0$
#1625
b10100011 "
b10100011 +
b11110010 !
b11110010 )
b11110010 *
b10100011 #
b10100011 (
b10100010 '
1$
#1630
0$
#1635
b10100100 "
b10100100 +
b11110110 !
b11110110 )
b11110110 *
b10100100 #
b10100100 (
b10100011 '
1$
#1640
0$
#1645
b10100101 "
b10100101 +
b11110111 !
b11110111 )
b11110111 *
b10100101 #
b10100101 (
b10100100 '
1$
#1650
0$
#1655
b10100110 "
b10100110 +
b11110101 !
b11110101 )
b11110101 *
b10100110 #
b10100110 (
b10100101 '
1$
#1660
0$
#1665
b10100111 "
b10100111 +
b11110100 !
b11110100 )
b11110100 *
b10100111 #
b10100111 (
b10100110 '
1$
#1670
0$
#1675
b10101000 "
b10101000 +
b11111100 !
b11111100 )
b11111100 *
b10101000 #
b10101000 (
b10100111 '
1$
#1680
0$
#1685
b10101001 "
b10101001 +
b11111101 !
b11111101 )
b11111101 *
b10101001 #
b10101001 (
b10101000 '
1$
#1690
0$
#1695
b10101010 "
b10101010 +
b11111111 !
b11111111 )
b11111111 *
b10101010 #
b10101010 (
b10101001 '
1$
#1700
0$
#1705
b10101011 "
b10101011 +
b11111110 !
b11111110 )
b11111110 *
b10101011 #
b10101011 (
b10101010 '
1$
#1710
0$
#1715
b10101100 "
b10101100 +
b11111010 !
b11111010 )
b11111010 *
b10101100 #
b10101100 (
b10101011 '
1$
#1720
0$
#1725
b10101101 "
b10101101 +
b11111011 !
b11111011 )
b11111011 *
b10101101 #
b10101101 (
b10101100 '
1$
#1730
0$
#1735
b10101110 "
b10101110 +
b11111001 !
b11111001 )
b11111001 *
b10101110 #
b10101110 (
b10101101 '
1$
#1740
0$
#1745
b10101111 "
b10101111 +
b11111000 !
b11111000 )
b11111000 *
b10101111 #
b10101111 (
b10101110 '
1$
#1750
0$
#1755
b10110000 "
b10110000 +
b11101000 !
b11101000 )
b11101000 *
b10110000 #
b10110000 (
b10101111 '
1$
#1760
0$
#1765
b10110001 "
b10110001 +
b11101001 !
b11101001 )
b11101001 *
b10110001 #
b10110001 (
b10110000 '
1$
#1770
0$
#1775
b10110010 "
b10110010 +
b11101011 !
b11101011 )
b11101011 *
b10110010 #
b10110010 (
b10110001 '
1$
#1780
0$
#1785
b10110011 "
b10110011 +
b11101010 !
b11101010 )
b11101010 *
b10110011 #
b10110011 (
b10110010 '
1$
#1790
0$
#1795
b10110100 "
b10110100 +
b11101110 !
b11101110 )
b11101110 *
b10110100 #
b10110100 (
b10110011 '
1$
#1800
0$
#1805
b10110101 "
b10110101 +
b11101111 !
b11101111 )
b11101111 *
b10110101 #
b10110101 (
b10110100 '
1$
#1810
0$
#1815
b10110110 "
b10110110 +
b11101101 !
b11101101 )
b11101101 *
b10110110 #
b10110110 (
b10110101 '
1$
#1820
0$
#1825
b10110111 "
b10110111 +
b11101100 !
b11101100 )
b11101100 *
b10110111 #
b10110111 (
b10110110 '
1$
#1830
0$
#1835
b10111000 "
b10111000 +
b11100100 !
b11100100 )
b11100100 *
b10111000 #
b10111000 (
b10110111 '
1$
#1840
0$
#1845
b10111001 "
b10111001 +
b11100101 !
b11100101 )
b11100101 *
b10111001 #
b10111001 (
b10111000 '
1$
#1850
0$
#1855
b10111010 "
b10111010 +
b11100111 !
b11100111 )
b11100111 *
b10111010 #
b10111010 (
b10111001 '
1$
#1860
0$
#1865
b10111011 "
b10111011 +
b11100110 !
b11100110 )
b11100110 *
b10111011 #
b10111011 (
b10111010 '
1$
#1870
0$
#1875
b10111100 "
b10111100 +
b11100010 !
b11100010 )
b11100010 *
b10111100 #
b10111100 (
b10111011 '
1$
#1880
0$
#1885
b10111101 "
b10111101 +
b11100011 !
b11100011 )
b11100011 *
b10111101 #
b10111101 (
b10111100 '
1$
#1890
0$
#1895
b10111110 "
b10111110 +
b11100001 !
b11100001 )
b11100001 *
b10111110 #
b10111110 (
b10111101 '
1$
#1900
0$
